Workbook

Sheet MATERIAL
A1: codigo | B1: Texto breve de material (REVISADA) | C1: Unidade de medida básica | D1: CODIGO SAP | E1: Peso bruto | F1: Unidade de peso | G1: Código ABC
A2: 90399 | B2: ESTRIBO P/ BRACO TIPO L ACO GALV 140X70X50MM 400DAN | C2: PC
A3: 90648 | B3: AFASTADOR ISOLADOR PILAR ACO GALV 100X320MM 10MM 320DAN | C3: PC | D3: 10016721 | E3: 1 | F3: KG | G3: C
A4: 90301 | B4: ALCA PREF CORD ACO-ZN 6,40MM 5X2.18MM 460MM AMR | C4: PÇ
A5: 90301 | B5: ALCA PREF CORD ACO-ZN 6,40MM 5X2.18MM 460MM AMR | C5: UN
A6: 90013 | B6: ALCA PREF CORD ACO-ZN 9,50MM 6X2.54MM 965MM LRJ | C6: PÇ | D6: 10000856 | E6: 0.245 | F6: KG | G6: C
A7: 90013 | B7: ALCA PREF CORD ACO-ZN 9,50MM 6X2.54MM 965MM LRJ | C7: UN | D7: CODIGO PADRÃO | E7: 4.02 | F7: KG | G7: C
A8: 113 | B8: ALCA PREF DIS CA/CAA 2/0AWG 10,4-11,69MM | C8: PC | D8: 10000857 | E8: 0.39 | F8: KG | G8: C
A9: 2814 | B9: ALCA PREF DIS CA/CAA 6AWG 4,62-5,15MM | C9: PC
A10: 90315 | B10: ALCA PREF DISTR ACO-ALUM 9,27-10,40MM 660MM AMR | C10: PC | D10: 10000846 | E10: 0.34 | F10: KG | G10: C
A11: 90315 | B11: ALCA PREF DISTR ACO-ALUM 9,27-10,40MM 660MM AMR | C11: UN | D11: 10000805 | E11: 0.895 | F11: KG | G11: C
A12: 90308 | B12: ALCA PREF DISTR ACO-ZINC 13,10-14,65MM 865MM VRM | C12: PC | D12: 10000800 | E12: 0.24 | F12: KG | G12: C
A13: 90308 | B13: ALCA PREF DISTR ACO-ZINC 13,10-14,65MM 865MM VRM 4/0 | C13: UN | D13: 10000809 | E13: 0.18 | F13: KG | G13: C
A14: 90309 | B14: ALCA PREF DISTR ACO-ZINC 16,20-18,15MM 980MM VRD | C14: UN | D14: 10000817 | E14: 0.6 | F14: KG | G14: C
A15: 90307 | B15: ALCA PREF DISTR ACO-ZINC 9,15-10,25MM 670MM AMR | C15: UN | D15: 10000849 | E15: 0.25 | F15: KG
A16: 121 | B16: ALCA PREF ESTAI 6,4MM HS/SM | D16: 10000840 | E16: 0.21 | F16: KG
A17: 121 | B17: ALCA PREF ESTAI 6,4MM HS/SM | C17: PC | D17: 10000808 | E17: 0.11 | F17: KG | G17: C
A18: 90303 | B18: ALCA PREF SERV ACO-ZINC 3,90-4,30MM 345MM MRM | C18: UN
A19: 90305 | B19: ALCA PREF SERV ACO-ZINC 6,00-6,70MM 330MM LRJ | C19: UN | D19: 10000807 | E19: 0.7 | F19: KG | G19: C
A20: 90305 | B20: ALCA PREF SERV ACO-ZINC 6,00-6,70MM 330MM LRJ | C20: UN | D20: 10000812 | E20: 0.032 | F20: KG
A21: 2815 | B21: ALCA PREFORMADA DISTRIBUICAO 2AWG 610,0MM | C21: PC | D21: 10000816 | E21: 0.31 | F21: KG
A22: 2815 | B22: ALCA PREFORMADA DISTRIBUICAO 2AWG 610,0MM | C22: PC | D22: 10000859 | E22: 0.4 | F22: KG | G22: C
A23: 2878 | B23: ALCA PREFORMADA SERVICO 8AWG 355,0MM | C23: PC | D23: 10000853 | E23: 0.18 | F23: KG | G23: C
A24: 2878 | B24: ALCA PREFORMADA SERVICO 8AWG 355,0MM | C24: PC | D24: 10000839 | E24: 0.46 | F24: KG | G24: C
A25: 90537 | B25: ANEL AMAR ELASTOMERICO P/ESPACADOR 45X90X140MM CNZ | C25: UN | D25: 10000867 | E25: 0.02 | F25: KG | G25: C
A26: 90538 | B26: ANEL AMAR ELASTOMERICO P/ISOLADOR 15,0KV 45X110X160MM VRM | C26: UN | D26: 10000868 | E26: 0.01 | F26: KG
A27: 90538 | B27: ANEL AMAR ELASTOMERICO P/ISOLADOR 15,0KV 45X110X160MM VRM | C27: UN
A28: 90538 | B28: ANEL AMARR ELASTOMERICO P/ISOLADOR 15,0KV 45X110X160MM VRM | C28: UN | D28: 10002607 | E28: 0.8 | F28: KG | G28: C
A29: 90300 | B29: ARAME REDOND ACO-GALV DURA 2,77MM BWG12 | C29: UN | D29: 10002607 | E29: 0.8 | F29: KG | G29: C
A30: 90300 | B30: ARAME REDOND ACO-GALV DURA 2,77MM BWG12 | C30: KG | D30: 10002608 | E30: 1.92 | F30: KG | G30: C
A31: 2966 | B31: ARMACAO SECUNDARIA ACO CARB 2 ESTRIBOS 5,0X 325,0X 310,0MM | C31: PÇ
A32: 2966 | B32: ARMACAO SECUNDARIA ACO CARB 2 ESTRIBOS 5,0X 325,0X 310,0MM | C32: PC | D32: 10002609 | E32: 3.06 | F32: KG
A33: 90393 | B33: ARMACAO SECUNDARIA ACO GALV 1 ESTRIBO 110X50X5,0MM 125X16MM | C33: PC | D33: 10002610 | E33: 4.055 | F33: KG | G33: C
A34: 90393 | B34: ARMACAO SECUNDARIA ACO GALV 1 ESTRIBO 110X50X5,0MM 125X16MM | C34: UN | D34: 10008218 | E34: 0.02 | F34: KG
A35: 92017 | B35: ARMACAO SECUNDARIA ACO GALV 2 ESTRIBO 310X50X5,0MM 325X16MM | C35: PC | D35: 10000872 | E35: 0.026 | F35: KG | G35: C
A36: 90893 | B36: ARRUELA ESPACADORA FERRO FUND 50X18X30MM | C36: PC | D36: 10000875 | E36: 0.55 | F36: KG | G36: C
A37: 3055 | B37: ARRUELA ESPACADORA LISA CIRCULAR FOFO GALV DIN9021 M18 | C37: PÇ | D37: 10000878 | E37: 0.5 | F37: KG | G37: C
A38: 90893 | B38: ARRUELA ESPACADORA LISA CIRCULAR FOFO GALV DIN9021 M18 | C38: PC | D38: 10000955 | E38: 9.2 | F38: KG | G38: C
A39: 90389 | B39: ARRUELA QUADRADA ACO GALV 38X18X3MM | C39: UN | D39: 10000995 | E39: 4.54 | F39: KG | G39: C
A40: 90389 | B40: ARRUELA QUADRADA ACO GALV 38X18X3MM | C40: UN
A41: 90540 | B41: BRACO ANTI-BALANCO PEAD 15,0KV 305MM | C41: PC | D41: 10000999 | G41: C
A42: 90540 | B42: BRACO ANTI-BALANCO PEAD 15,0KV 305MM | C42: UN | D42: 10000989 | G42: C
A43: 90540 | B43: BRACO ANTIBALANCO PEAD 15,0KV 305MM CNZ/PRT 180/50DAN | C43: UN | D43: 10000899 | G43: B
A44: 90542 | B44: BRACO COMP TIPO C 15KV ACO-GALV 580X365X362MM | C44: UN | D44: 10000919
A45: 90544 | B45: BRACO COMP TIPO L 15KV ACO-GALV 354X241MM | C45: UN | D45: 10000921 | E45: 0.4 | F45: KG
A46: 90513 | B46: BRACO COMP TIPO L 36,2KV ACO-GALV 600X241MM | C46: UN | D46: 10000902 | E46: 1 | F46: KG | G46: C
A47: 90536 | B47: BRACO COMP.TIPO J 15/36,2 KV ACO-GALV 1650X550MM | C47: PC | D47: 10000370 | E47: 0.1 | F47: KG | G47: A
A48: 90542 | B48: BRACO REDE COMP TIPO C 15KV SAE1010/20 580MM | C48: PC | D48: 10000881 | E48: 1 | F48: KG | G48: C
A49: 90544 | B49: BRACO REDE COMP TIPO L 15KV SAE1010/20 354MM | C49: PÇ | D49: 10000918 | E49: 0.92 | F49: KG
A50: 90272 | B50: CABO ALUM MULTIPLEX 0,6/1,0KV XLPE 1F 1X1X10MM2+10MM2 | C50: M | D50: 10000924 | E50: 1.78 | F50: KG | G50: C
A51: 90290 | B51: CABO ALUM MULTIPLEX 0,6/1,0KV XLPE 3F 3X1X120MM2+70MM2 | C51: M | D51: 10000892 | E51: 1 | F51: KG | G51: C
A52: 90287 | B52: CABO ALUM MULTIPLEX 0,6/1,0KV XLPE 3F 3X1X25MM2+25MM2 | C52: M | D52: 10000898 | E52: 1.1 | F52: KG
A53: 90288 | B53: CABO ALUM MULTIPLEX 0,6/1,0KV XLPE 3F 3X1X35MM2+35MM2 | C53: M
A54: 90289 | B54: CABO ALUM MULTIPLEX 0,6/1,0KV XLPE 3F 3X1X70MM2+70MM2 | C54: M
A55: 90274 | B55: CABO ALUM MULTIPLEX 0,6/1KV XLPE 2F 10MM2+10MM2 | C55: M | D55: 10000917 | G55: A
A56: 90290 | B56: CABO ALUM MULTIPLEX 0,6/1KV XLPE 3F 120MM2+70MM2 | C56: M | D56: 10000896 | E56: 0.94 | F56: KG
A57: 90288 | B57: CABO ALUM MULTIPLEX 0,6/1KV XLPE 3F 35MM2+35MM2 | C57: M | D57: 10000885 | E57: 1 | F57: KG | G57: C
A58: 90289 | B58: CABO ALUM MULTIPLEX 0,6/1KV XLPE 3F 70MM2+70MM2 | C58: M | D58: 10000901 | E58: 1 | F58: KG | G58: C
A59: 90259 | B59: CABO ALUM NU 1F CA/AAC 1/0AWG POPPY | C59: KG | D59: 10000882 | E59: 1 | F59: KG | G59: C
A60: 90259 | B60: CABO ALUM NU 1F CA/AAC 1/0AWG POPPY -NEUTRO- | C60: KG | D60: 10000883 | E60: 1 | F60: KG
A61: 90258 | B61: CABO ALUM NU 1F CA/AAC 2AWG IRIS | C61: KG | D61: 10000889 | E61: 1 | F61: KG
A62: 90258 | B62: CABO ALUM NU 1F CA/AAC 2AWG IRIS- FASES- | C62: KG | D62: 10011182 | E62: 1 | F62: KG | G62: C
A63: 690327 | B63: CABO ALUM NU 1F CA/AAC 336,4MCM TULIP | C63: KG | D63: 10000884 | E63: 1 | F63: KG | G63: C
A64: 90261 | B64: CABO ALUM NU 1F CA/AAC 336,4MCM TULIP | C64: KG | D64: 10008572 | E64: 1 | F64: KG | G64: A
A65: 621837 | B65: CABO ALUM NU CA 6AWG 1F SWAN | C65: KG | D65: 10008867 | E65: 1 | F65: KG
A66: 90263 | B66: CABO ALUM NU CAA 1/0AWG 1F RAVEN | C66: KG | D66: 10008864 | E66: 1 | F66: KG | G66: A
A67: 90262 | B67: CABO ALUM NU CAA 2AWG 1F SPARROW | C67: KG
A68: 90560 | B68: CABO ALUM NU CAA 4AWG 1F SWAN | C68: KG | D68: 10000077 | E68: 1 | F68: KG | G68: C
A69: 90263 | B69: CABO ALUM NU CAA/ASCR 1F 1/0AWG RAVEN | C69: KG | D69: 10001012 | E69: 1 | F69: KG | G69: C
A70: 90262 | B70: CABO ALUM NU CAA/ASCR 1F 2AWG SPARROW | D70: 10000962 | E70: 0.4 | F70: KG
A71: 90264 | B71: CABO ALUM NU CAA/ASCR 1F 4/0AWG PENGUIN | C71: KG | D71: 10000962 | E71: 0.4 | F71: KG
A72: 90267 | B72: CABO ALUM PROT SPL 120MM2 15,0KV 1F 15 FIOS | C72: M
A73: 90268 | B73: CABO ALUM PROT SPL 15,0KV 185MM2 1F 30 FIOS | C73: M | D73: 10017869 | E73: 1 | F73: KG
A74: 90266 | B74: CABO ALUM PROT SPL 15,0KV 50MM2 1F | C74: M | D74: 10001014 | E74: 0.721 | F74: KG | G74: A
A75: 90267 | B75: CABO ALUM PROT SPL XLPE 1F 15,0KV 120MM2 BLOQ CNZ | C75: M | D75: 10001016 | E75: 0.844 | F75: KG | G75: B
A76: 91206 | B76: CABO ALUM PROT SPL XLPE 1F 15,0KV 150MM2 BLOQ CNZ | C76: M | D76: 10000373 | E76: 0.163 | F76: KG | G76: A
A77: 90266 | B77: CABO ALUM PROT SPL XLPE 1F 15,0KV 50MM2 BLOQ CNZ | C77: M
A78: 90292 | B78: CABO ALUM PROT SPL XLPE 1F 36,2KV 120MM2 BLOQ CNZ | C78: M | D78: 10000979 | G78: A
A79: 90291 | B79: CABO ALUM PROT SPL XLPE 1F 36,2KV 70MM2 BLOQ CNZ | C79: M | D79: 10000969 | G79: C
A80: 90294 | B80: CABO COBR PROT SPL XLPE 1F 15,0KV 16MM2 BLOQ CNZ | C80: M
A81: 91217 | B81: CABO COBRE ISOLAD 450/750V BWF/PVC 10MM2 CL2/4/5 | C81: M
A82: 91462 | B82: CABO COBRE ISOLAD 450/750V BWF/PVC 120MM2 CL2/4/5 PRT | C82: M | D82: 10000983 | E82: 1.78 | F82: KG
A83: 91462 | B83: CABO COBRE ISOLAD 450/750V BWF/PVC 120MM2 CL2/4/5 PRT | C83: M | D83: 10000927 | G83: C
A84: 91462 | B84: CABO COBRE ISOLADOR 120MM | C84: M | D84: 10001023 | E84: 0.525 | F84: KG | G84: C
A85: 623 | B85: CABO COBRE ISOLADOR 120MM | C85: M
A86: 623984 | B86: CABO CONTROLE 1KV COBRE PVC 2X2,5MM2 CL2 | C86: M | D86: 10000286 | E86: 1.28 | F86: KG | G86: C
A87: 3098 | B87: CABO ISOL 750V COBRE PVC/BWF 10MM2 1F CL2 PT | C87: M | D87: 10000400 | E87: 0.3 | F87: KG | G87: C
A88: 3098 | B88: CABO ISOL 750V COBRE PVC/BWF 10MM2 1F CL2 PT | C88: M | D88: 10000363 | E88: 0.1 | F88: KG | G88: C
A89: 90294 | B89: CABO PROT SPL COBRE 16MM2 15,0KV 1F 6 FIOS | C89: M | D89: 10000372 | E89: 0.15 | F89: KG | G89: C
A90: 4475 | B90: CAPA ISOL CONECTOR CUNHA 15KV PE | C90: PÇ | D90: 10002632 | E90: 11 | F90: KG
A91: 90887 | B91: CAPA PROT CONECTOR CUNHA 15KV 131X80MM SERIE VERM | C91: PC | D91: 10002633 | G91: C
A92: 90888 | B92: CAPA PROT CONECTOR CUNHA 15KV 166X100MM SERIE AZUL | C92: PC | D92: 10002634 | E92: 17 | F92: KG
A93: 90968 | B93: CAPA PROT PEAD TRANSF BT 1,2 KV 247X85X70MM 2X24MM | C93: PÇ | D93: 10002635 | G93: A
A94: 90968 | B94: CAPA PROT PEAD TRANSF BT 1,2 KV 247X85X70MM 2X24MM | C94: UN | D94: 10002636 | E94: 21 | F94: KG | G94: A
A95: 90586 | B95: CAPA PROT PEAD TRANSF MT 15/36,2KV 135X110MM | C95: UN | D95: 10002637 | E95: 0.001 | F95: KG | G95: C
A96: 90586 | B96: CAPA PROT PEAD TRANSF MT 15/36,2KV 135X110MM | C96: UN
A97: 90586 | B97: CAPA PROT PEAD TRANSF MT 15/36,2KV 135X110MM | C97: UN
A98: 90486 | B98: CARTUCHO FERRAM CONECTOR CUNHA AMARELO 24,30MM | C98: PC
A99: 90486 | B99: CARTUCHO FERRAM CONECTOR CUNHA AMARELO 24,30MM | C99: UN | D99: 10002638 | E99: 0.001 | F99: KG | G99: C
A100: 90487 | B100: CARTUCHO FERRAM CONECTOR CUNHA AZUL 14,80MM | C100: PC
...

Sheet RELAÇAO DE MATERIAL
A1: cod_material | B1: descricao | C1: und_medida | D1: val_material | E1: situacao | F1: qtd_item_prev | G1: qtd_rma | H1: qtd_outros | I1: qtd_dma | J1: qtdmat_apl | K1: qtdmat_apl_fsc
A2: 90399 | B2: ESTRIBO P/ BRACO TIPO L ACO GALV 140X70X50MM 400DAN | C2: UN | D2: 12 | E2: NORMAL | F2: 2 | G2: 2 | H2: 0 | I2: 0 | K2: 2
A3: 90013 | B3: ALCA PREF CORD ACO-ZN 9,50MM 6X2.54MM 965MM LRJ | C3: UN | D3: 6.76 | E3: NORMAL | F3: 10 | G3: 6 | H3: 0 | I3: 0 | K3: 4
A4: 90315 | B4: ALCA PREF DISTR ACO-ALUM 9,27-10,40MM 660MM AMR | C4: UN | D4: 4.35 | E4: NORMAL | F4: 32 | G4: 14 | H4: 0 | I4: 0 | K4: 0
A5: 90308 | B5: ALCA PREF DISTR ACO-ZINC 13,10-14,65MM 865MM VRM | C5: UN | D5: 8.08 | E5: NORMAL | F5: 48 | G5: 36 | H5: 0 | I5: 0 | K5: 0
A6: 121 | B6: ALCA PREF ESTAI 6,4MM HS/SM | C6: PC | D6: 3.03 | E6: NORMAL | F6: 26 | G6: 13 | H6: 0 | I6: 0 | K6: 0
A7: 90305 | B7: ALCA PREF SERV ACO-ZINC 6,00-6,70MM 330MM LRJ | C7: UN | D7: 1.05 | E7: NORMAL | F7: 5 | G7: 0 | H7: 0 | I7: 0 | K7: 0
A8: 2815 | B8: ALCA PREFORMADA DISTRIBUICAO 2AWG 610,0MM | C8: PC | D8: 3.53 | E8: NORMAL | F8: 97 | G8: 19 | H8: 0 | I8: 0 | K8: 0
A9: 2878 | B9: ALCA PREFORMADA SERVICO 8AWG 355,0MM | C9: PC | D9: 0.58 | E9: NORMAL | F9: 0 | G9: 2 | H9: 0 | I9: 0 | K9: 0
A10: 90538 | B10: ANEL AMAR ELASTOMERICO P/ISOLADOR 15,0KV 45X110X160MM VRM | C10: UN | D10: 2.26 | E10: NORMAL | F10: 9 | G10: 3 | H10: 0 | I10: 0 | K10: 0
A11: 90300 | B11: ARAME REDOND ACO-GALV DURA 2,77MM BWG12 | C11: KG | D11: 21.32 | E11: NORMAL | F11: 1 | G11: 0 | H11: 0 | I11: 0 | K11: 0
A12: 2966 | B12: ARMACAO SECUNDARIA ACO CARB 2 ESTRIBOS 5,0X 325,0X 310,0MM | C12: PC | D12: 14.92 | E12: NORMAL | F12: 18 | G12: 4 | H12: 0 | I12: 0 | K12: 0
A13: 90393 | B13: ARMACAO SECUNDARIA ACO GALV 1 ESTRIBO 110X50X5,0MM 125X16MM | C13: UN | D13: 7.87 | E13: NORMAL | F13: 8 | G13: 1 | H13: 0 | I13: 0 | K13: 0
A14: 90893 | B14: ARRUELA ESPACADORA LISA CIRCULAR FOFO GALV DIN9021 M18 | C14: PC | D14: 14.5 | E14: DESPADRONIZADO | F14: 11 | G14: 8 | H14: 0 | I14: 0 | K14: 8
A15: 90389 | B15: ARRUELA QUADRADA ACO GALV 38X18X3MM | C15: UN | D15: 0.36 | E15: NORMAL | F15: 224 | G15: 70 | H15: 0 | I15: 0 | J15: 0 | K15: 2
A16: 90540 | B16: BRACO ANTI-BALANCO PEAD 15,0KV 305MM | C16: UN | D16: 12.7 | E16: NORMAL | F16: 2 | G16: 2 | H16: 0 | I16: 0 | K16: 2
A17: 90542 | B17: BRACO REDE COMP TIPO C 15KV SAE1010/20 580MM | C17: UN | D17: 52.56 | E17: NORMAL | F17: 3 | G17: 1 | H17: 0 | I17: 0 | K17: 0
A18: 90544 | B18: BRACO REDE COMP TIPO L 15KV SAE1010/20 354MM | C18: UN | D18: 44.78 | E18: NORMAL | F18: 2 | G18: 2 | H18: 0 | I18: 0 | K18: 2
A19: 90274 | B19: CABO ALUM MULTIPLEX 0,6/1KV XLPE 2F 10MM2+10MM2 | C19: M | D19: 3.8065 | E19: NORMAL | F19: 0 | G19: 5 | H19: 0 | I19: 0 | K19: 0
A20: 90290 | B20: CABO ALUM MULTIPLEX 0,6/1KV XLPE 3F 120MM2+70MM2 | C20: M | D20: 43.24 | E20: NORMAL | F20: 960 | G20: 180 | H20: 0 | I20: 0 | K20: 0
A21: 90288 | B21: CABO ALUM MULTIPLEX 0,6/1KV XLPE 3F 35MM2+35MM2 | C21: M | D21: 12.06 | E21: NORMAL | F21: 60.3 | G21: 60 | H21: 0 | I21: 0 | K21: 0
A22: 90289 | B22: CABO ALUM MULTIPLEX 0,6/1KV XLPE 3F 70MM2+70MM2 | C22: M | D22: 17.26 | E22: NORMAL | F22: 80 | G22: 0 | H22: 0 | I22: 0 | J22: 0 | K22: 0
A23: 90259 | B23: CABO ALUM NU 1F CA/AAC 1/0AWG POPPY | C23: KG | D23: 14.33 | E23: NORMAL | F23: 331.56 | G23: 0 | H23: 0 | I23: 0 | J23: 0 | K23: 0
A24: 90258 | B24: CABO ALUM NU 1F CA/AAC 2AWG IRIS | C24: KG | D24: 43.48 | E24: NORMAL | F24: 317.47 | G24: 74 | H24: 0 | I24: 0 | J24: 0 | K24: 0
A25: 690327 | B25: CABO ALUM NU 1F CA/AAC 336,4MCM TULIP | C25: KG | D25: 36.5054 | E25: NORMAL | F25: 1935 | G25: 0 | H25: 0 | I25: 1935 | J25: 0 | K25: 0
A26: 90263 | B26: CABO ALUM NU CAA 1/0AWG 1F RAVEN | C26: KG | D26: 36.04 | E26: NORMAL | F26: 0.65 | G26: 0.65 | H26: 0 | I26: 0 | K26: 0.65
A27: 90262 | B27: CABO ALUM NU CAA 2AWG 1F SPARROW | C27: KG | D27: 25.97 | E27: NORMAL | F27: 225.76 | G27: 0 | H27: 0 | I27: 0 | K27: 0
A28: 90560 | B28: CABO ALUM NU CAA 4AWG 1F SWAN | C28: KG | D28: 14.64 | E28: NORMAL | F28: 108.36 | G28: 0 | H28: 0 | I28: 0 | J28: 0 | K28: 0
A29: 90267 | B29: CABO ALUM PROT SPL 120MM2 15,0KV 1F 15 FIOS | C29: M | D29: 14.52 | E29: NORMAL | F29: 60 | G29: 0 | H29: 0 | I29: 0 | J29: 0 | K29: 0
A30: 90266 | B30: CABO ALUM PROT SPL 120MM2 15,0KV 1F 15 FIOS | C30: M | D30: 14.52
A31: 90268 | B31: CABO ALUM PROT SPL 15,0KV 185MM2 1F 30 FIOS | C31: M | D31: 21.09 | E31: NORMAL | F31: 705 | G31: 505 | H31: 0 | I31: 30 | K31: 355
A32: 91462 | B32: CABO COBRE ISOLAD 450/750V BWF/PVC 120MM2 CL2/4/5 PRT | C32: M | D32: 87.4 | E32: NORMAL | F32: 66 | G32: 24 | H32: 0 | I32: 0 | K32: 0
A33: 623984 | B33: CABO CONTROLE 1KV COBRE PVC 2X2,5MM2 CL2 | C33: M | D33: 5.58 | E33: NORMAL | F33: 10 | G33: 0 | H33: 0 | I33: 0 | K33: 0
A34: 3098 | B34: CABO ISOL 750V COBRE PVC/BWF 10MM2 1F CL2 PT | C34: M | D34: 7.64 | E34: NORMAL | F34: 64 | G34: 20 | H34: 0 | I34: 10 | J34: 0 | K34: 0
A35: 90294 | B35: CABO PROT SPL COBRE 16MM2 15,0KV 1F 6 FIOS | C35: M | D35: 16.67 | E35: NORMAL | F35: 143 | G35: 30 | H35: 0 | I35: 4 | J35: 0 | K35: 0
A36: 4475 | B36: CAPA ISOL CONECTOR CUNHA 15KV PE | C36: PC | D36: 5 | E36: DESPADRONIZADO | F36: 6 | G36: 3 | H36: 0 | I36: 0 | K36: 0
A37: 90968 | B37: CAPA PROT PEAD TRANSF BT 1,2 KV 247X85X70MM 2X24MM | C37: UN | D37: 24.42 | E37: NORMAL | F37: 69 | G37: 24 | H37: 0 | I37: 0 | K37: 0
A38: 90586 | B38: CAPA PROT PEAD TRANSF MT 15/36,2KV 135X110MM | C38: UN | D38: 7.54 | E38: NORMAL | F38: 64 | G38: 38 | H38: 0 | I38: 12 | J38: 0 | K38: 0
A39: 90486 | B39: CARTUCHO FERRAM CONECTOR CUNHA AMARELO 24,30MM | C39: UN | D39: 0.7 | E39: NORMAL | F39: 1 | G39: 0 | H39: 0 | I39: 0 | K39: 0
A40: 90487 | B40: CARTUCHO FERRAM CONECTOR CUNHA AZUL 14,80MM | C40: UN | D40: 0.47 | E40: NORMAL | F40: 455 | G40: 210 | H40: 0 | I40: 30 | J40: 0 | K40: 33
A41: 2900 | B41: CARTUCHO FERRAM CONECTOR CUNHA VERMELHO | C41: PC | D41: 2.33 | E41: DESPADRONIZADO | F41: 40 | G41: 0 | H41: 0 | I41: 0 | K41: 0
A42: 90488 | B42: CARTUCHO FERRAM CONECTOR CUNHA VERMELHO 14,80MM | C42: UN | D42: 2.12 | E42: NORMAL | F42: 76 | G42: 36 | H42: 0 | I42: 3 | K42: 0
A43: 90547 | B43: CHAVE FUS DIST PRC BASE C 15,0KV 315A 1F MAN SEC | C43: PC | D43: 261.07 | E43: NORMAL | F43: 14 | G43: 1 | H43: 0 | I43: 0 | J43: 0 | K43: 0
A44: 90548 | B44: CHAVE FUS DIST PRC BASE C 36,2KV 315A 1F MAN SEC | C44: PC | D44: 187.24 | E44: NORMAL | F44: 2 | G44: 2 | H44: 0 | I44: 1 | K44: 0
A45: 90550 | B45: CHAVE FUS RELIG DIST PRC BASE C 36,2KV 315A 1F MAN SEC 3INT | C45: PC | D45: 897.52 | E45: NORMAL | F45: 7 | G45: 0 | H45: 0 | I45: 0 | J45: 0 | K45: 0
A46: 90554 | B46: CHAVE SECC FACA PORC EXT 11,4-13,8-15KV 630A 1F MAN SECO CEN | C46: PC | D46: 517.66 | E46: NORMAL | F46: 30 | G46: 15 | H46: 0 | I46: 0 | J46: 0 | K46: 6
A47: 90553 | B47: CHAVE SECC FACA PORC EXT 34,5-36,2KV 400A 1F MAN SECO CENT | C47: PC | D47: 615.7 | E47: NORMAL | F47: 40 | G47: 3 | H47: 0 | I47: 0 | J47: 0 | K47: 0
A48: 90215 | B48: CINTA POSTE CIRCULAR ACO GALV 160MM 6MM 5000DAN | C48: UN | D48: 19.38 | E48: NORMAL | F48: 2 | G48: 0 | H48: 0 | I48: 0 | K48: 0
A49: 90216 | B49: CINTA POSTE CIRCULAR ACO GALV 170MM 6MM 5000DAN | C49: UN | D49: 14.33 | E49: NORMAL | F49: 11 | G49: 0 | H49: 0 | I49: 0 | K49: 0
A50: 90217 | B50: CINTA POSTE CIRCULAR ACO GALV 180MM 6MM 5000DAN | C50: UN | D50: 20.58 | E50: NORMAL | F50: 11 | G50: 0 | H50: 0 | I50: 0 | K50: 0
A51: 90218 | B51: CINTA POSTE CIRCULAR ACO GALV 190MM 6MM 5000DAN | C51: UN | D51: 15.07 | E51: NORMAL | F51: 16 | G51: 3 | H51: 0 | I51: 2 | J51: 0 | K51: 0
A52: 90219 | B52: CINTA POSTE CIRCULAR ACO GALV 200MM 6MM 5000DAN | C52: UN | D52: 14.82 | E52: NORMAL | F52: 13 | G52: 6 | H52: 0 | I52: 2 | J52: 0 | K52: 0
A53: 90231 | B53: CINTA POSTE CIRCULAR ACO GALV 210MM 6MM 5000DAN | C53: UN | D53: 15.24 | E53: NORMAL | F53: 4 | G53: 3 | H53: 0 | I53: 0 | K53: 1
A54: 90220 | B54: CINTA POSTE CIRCULAR ACO GALV 220MM 6MM 5000DAN | C54: UN | D54: 15.67 | E54: NORMAL | F54: 3 | G54: 3 | H54: 0 | I54: 0 | K54: 2
A55: 90221 | B55: CINTA POSTE CIRCULAR ACO GALV 230MM 6MM 5000DAN | C55: UN | D55: 15.63 | E55: NORMAL | F55: 5 | G55: 5 | H55: 0 | I55: 0 | K55: 3
A56: 90222 | B56: CINTA POSTE CIRCULAR ACO GALV 240MM 6MM 5000DAN | C56: UN | D56: 16.7 | E56: NORMAL | F56: 6 | G56: 6 | H56: 0 | I56: 0 | K56: 4
A57: 90223 | B57: CINTA POSTE CIRCULAR ACO GALV 250MM 6MM 5000DAN | C57: UN | D57: 17.95 | E57: NORMAL | F57: 5 | G57: 5 | H57: 0 | I57: 0 | K57: 3
A58: 90232 | B58: CINTA POSTE CIRCULAR ACO GALV 260MM 6MM 5000DAN | C58: UN | D58: 226.38 | E58: NORMAL | F58: 3 | G58: 4 | H58: 0 | I58: 0 | K58: 2
A59: 90224 | B59: CINTA POSTE CIRCULAR ACO GALV 270MM 6MM 5000DAN | C59: UN | D59: 20.04 | E59: NORMAL | F59: 3 | G59: 4 | H59: 0 | I59: 0 | K59: 2
A60: 90225 | B60: CINTA POSTE CIRCULAR ACO GALV 280MM 6MM 5000DAN | C60: UN | D60: 14.24 | E60: NORMAL | F60: 4 | G60: 5 | H60: 0 | I60: 0 | K60: 2
A61: 90233 | B61: CINTA POSTE CIRCULAR ACO GALV 290MM 6MM 5000DAN | C61: UN | D61: 19.08 | E61: NORMAL | F61: 4 | G61: 3 | H61: 0 | I61: 0 | K61: 2
A62: 90226 | B62: CINTA POSTE CIRCULAR ACO GALV 300MM 6MM 5000DAN | C62: UN | D62: 22.79 | E62: NORMAL | F62: 2 | G62: 1 | H62: 0 | I62: 1 | K62: 0
A63: 90227 | B63: CINTA POSTE CIRCULAR ACO GALV 310MM 6MM 5000DAN | C63: UN | D63: 21.34 | E63: NORMAL | F63: 1 | G63: 0 | H63: 0 | I63: 0 | K63: 0
A64: 90235 | B64: CINTA POSTE CIRCULAR ACO GALV 340MM 6MM 5000DAN | C64: UN | D64: 22.56 | E64: NORMAL | F64: 0 | G64: 2 | H64: 0 | I64: 0 | K64: 0
... A71: 90472 | B71: CONEC CUNHA RML COBR TP II 3,17-8,12/3,17-5,21MM VD | C71: UN | D71: 1.06 | E71: NORMAL | F71: 4 | G71: 0 | H71: 0 | I71: 0 | K71: 0
A72: 90490 | B72: CONECTOR ATERR CUNHA COBRE CB/HST 16-25MM2 14,3MM | C72: UN | D72: 8.47 | E72: NORMAL | F72: 34 | G72: 40 | H72: 0 | I72: 0 | J72: 0 | K72: 0
A73: 90113 | B73: CONECTOR CUNHA ALUM CN-01 16,30-18,50/15,00-18,50MM AZL | C73: PC | D73: 6.14 | E73: NORMAL | F73: 8 | G73: 0 | H73: 0 | I73: 0 | K73: 0
A74: 90799 | B74: CONECTOR CUNHA ALUM CN-03 15,24-17,37/8,23-15,24MM AZL | C74: UN | D74: 10.31 | E74: NORMAL | F74: 68 | G74: 62 | H74: 0 | I74: 0 | K74: 0
A75: 90790 | B75: CONECTOR CUNHA ALUM CN-06 9,25-14,53/6,55-14,53MM AZL | C75: UN | D75: 15.15 | E75: NORMAL | F75: 49 | G75: 25 | H75: 0 | I75: 0 | J75: 0 | K75: 0
A76: 90791 | B76: CONECTOR CUNHA ALUM CN-10 8,23-14,53/4,11-11,79MM AZL | C76: UN | D76: 8.86 | E76: NORMAL | F76: 19 | G76: 1 | H76: 0 | I76: 0 | J76: 0 | K76: 0
A77: 90795 | B77: CONECTOR CUNHA ALUM CN-16 16,90-18,30/11,80-14,31MM AZL | C77: UN | D77: 6.44 | E77: NORMAL | F77: 6 | G77: 0 | H77: 0 | I77: 0 | K77: 0
A78: 90800 | B78: CONECTOR CUNHA ALUM CN-17 16,90-18,30/7,42-11,35MM AZL | C78: UN | D78: 14.86 | E78: NORMAL | F78: 6 | G78: 0 | H78: 0 | I78: 0 | K78: 0
A79: 3057 | B79: CONECTOR CUNHA ALUMINIO 1/0 - 2/0 AWG / 2 AWG AZ | C79: PC | D79: 14.58 | E79: DESPADRONIZADO | F79: 1 | G79: 0 | H79: 0 | I79: 0 | K79: 0
A80: 2914 | B80: CONECTOR CUNHA ALUMINIO 10,11MM/ 8,38MM VM | C80: PC | D80: 2.25 | E80: DESPADRONIZADO | F80: 20 | G80: 3 | H80: 0 | I80: 0 | K80: 3
A81: 2915 | B81: CONECTOR CUNHA ALUMINIO 14,53MM/ 11,79MM AZ | C81: PC | D81: 5.39 | E81: DESPADRONIZADO | F81: 2 | G81: 12 | H81: 0 | I81: 6 | J81: 0 | K81: 6
A82: 2916 | B82: CONECTOR CUNHA ALUMINIO 14,53MM/ 14,53MM AZ | C82: PC | D82: 8.98 | E82: DESPADRONIZADO | F82: 68 | G82: 12 | H82: 0 | I82: 0 | K82: 12
A83: 2917 | B83: CONECTOR CUNHA ALUMINIO 15,24MM/ 14,27MM AZ | C83: PC | D83: 4.77 | E83: DESPADRONIZADO | F83: 32 | G83: 30 | H83: 0 | I83: 6 | K83: 18
A84: 3058 | B84: CONECTOR CUNHA ALUMINIO 336,4MCM/ 1/0AWG AM ESTRIBO | C84: PC | D84: 29.5 | E84: DESPADRONIZADO | F84: 1 | G84: 1 | H84: 0 | I84: 0 | K84: 0
A85: 3913 | B85: CONECTOR CUNHA ALUMINIO 4/0AWG/ 2AWG AZ | C85: PC | D85: 10.76 | E85: DESPADRONIZADO | F85: 3 | G85: 0 | H85: 0 | I85: 0 | K85: 0
A86: 2913 | B86: CONECTOR CUNHA ALUMINIO 4/0AWG/ 4/0AWG AZ | C86: PC | D86: 5.39 | E86: DESPADRONIZADO | F86: 3 | G86: 0 | H86: 0 | I86: 0 | K86: 0
A87: 90348 | B87: CONECTOR CUNHA CB-EST ALUM 14,88-16,30MM 1/0AWG AM | C87: UN | D87: 25.34 | E87: NORMAL | F87: 1 | G87: 0 | H87: 0 | I87: 0 | K87: 0
A88: 90345 | B88: CONECTOR CUNHA CB-EST ALUM 5,88-8,01MM 2AWG VM | C88: UN | D88: 17.71 | E88: NORMAL | F88: 16 | G88: 2 | H88: 0 | I88: 0 | K88: 0
A89: 2902 | B89: CONECTOR CUNHA COBRE 25MM2/ 14,30MM AM | C89: PC | D89: 4.64 | E89: DESPADRONIZADO | F89: 100 | G89: 18 | H89: 0 | I89: 0 | K89: 18
A90: 2919 | B90: CONECTOR CUNHA COBRE 8,12MM/ 5,21MM VD | C90: PC | D90: 1.21 | E90: DESPADRONIZADO | F90: 9 | G90: 4 | H90: 0 | I90: 0 | K90: 4
A91: 90353 | B91: CONECTOR DERIV PERFURAT C/C 1,0KV 16-120MM2/4-35MM2 | C91: UN | D91: 8.6 | E91: NORMAL | F91: 41 | G91: 12 | H91: 0 | I91: 0 | K91: 0
A92: 90357 | B92: CONECTOR DERIV PERFURAT C/C 1,0KV 70-240MM2/70-240MM2 | C92: UN | D92: 6.6 | E92: NORMAL | F92: 88 | G92: 24 | H92: 0 | I92: 0 | K92: 0
A93: 90461 | B93: CONECTOR GRAMPO LINHA VIVA ALUM 35-120MM2/ 10-95MM2 400A | C93: UN | D93: 72.29 | E93: NORMAL | F93: 1 | G93: 0 | H93: 0 | I93: 0 | K93: 0
A94: 90460 | B94: CONECTOR GRAMPO LINHA VIVA COBRE 2-1/0AWG/ 8-2/0AWG 100A | C94: UN | D94: 66.46 | E94: NORMAL | F94: 5 | G94: 5 | H94: 0 | I94: 0 | K94: 0
A95: 90255 | B95: CORDOALHA ACO CARB CL A 7 FIOS MR 6,4MM 1430DAN | C95: M | D95: 3.28 | E95: NORMAL | F95: 502 | G95: 482 | H95: 0 | I95: 24 | J95: 0 | K95: 72
A96: 90256 | B96: CORDOALHA ACO CARB CL A 7 FIOS MR 9,5MM 3160DAN | C96: M | D96: 6.79 | E96: NORMAL | F96: 140 | G96: 140 | H96: 0 | I96: 0 | K96: 140
A97: 90404 | B97: CRUZETA DISTR PRFV TIPO RET 2400MM 90X112,5MM 400DAN CL2 | C97: UN | D97: 177.42 | E97: NORMAL | F97: 93 | G97: 29 | H97: 0 | I97: 2 | J97: 0 | K97: 10
A98: 2988 | B98: CRUZETA POSTE MADEIRA RETANGULAR 2400MM | C98: PC | D98: 78.26 | E98: DESPADRONIZADO | F98: 17 | G98: 0 | H98: 0 | I98: 0 | J98: 0 | K98: 0
A99: 35797 | B99: ELETRODUTO RIGIDO PVC PRETO BSP 1/2 | C99: PC | D99: 6.8636 | E99: NORMAL | F99: 2 | G99: 2 | H99: 0 | I99: 0 | K99: 1
A100: 3062 | B100: ELO FUSIVEL DISTRIBUICAO H 0,75A 500MM | C100: PC | D100: 3.4 | E100: DESPADRONIZADO | F100: 1 | G100: 0 | H100: 0 | I100: 0 | K100: 0
A101: 90498 | B101: ELO FUSIVEL DISTRIBUICAO TIPO H 1A 500MM | C101: UN | D101: 4.6667 | E101: NORMAL | F101: 1 | G101: 0 | H101: 0 | I101: 0 | K101: 0
A102: 90501 | B102: ELO FUSIVEL DISTRIBUICAO TIPO H 5A 500MM | C102: UN | D102: 4.6667 | E102: NORMAL | F102: 27 | G102: 6 | H102: 0 | I102: 0 | K102: 0
A103: 90508 | B103: ELO FUSIVEL DISTRIBUICAO TIPO K 25A 500MM | C103: UN | D103: 4.27 | E103: DESPADRONIZADO | F103: 3 | G103: 0 | H103: 0 | I103: 0 | K103: 0
A104: 90639 | B104: ELO FUSIVEL DISTRIBUICAO TIPO K 6A 500MM AMARELA | C104: UN | D104: 5.2473 | E104: NORMAL | F104: 12 | G104: 6 | H104: 0 | I104: 0 | J104: 0 | K104: 0
A105: 90124 | B105: EMENDA PREF COND LIGA ALUM TCAA 336,40MCM 910MM | C105: PC | D105: 109.99 | E105: NORMAL | F105: 6 | G105: 0 | H105: 0 | I105: 0 | J105: 0 | K105: 0
A106: 90406 | B106: ESPACADOR LOSANG PEAD 15,0KV 340X460MM ANEL 3 COND | C106: UN | D106: 14.01 | E106: NORMAL | F106: 2 | G106: 2 | H106: 0 | I106: 0 | K106: 0
...

Sheet Página8

Sheet CONTRATO 2024014901
A1: cod_grupo | B1: descricao | C1: cod_mobra | D1: descricao | E1: instalar | F1: retirar | G1: instalar_emergencial | H1: retirar_emergencial
A2: 500 | B2: SAP | C2: 92525 | D2: SERV. EMERG. HORARIO COMERCIAL - ADICIONAL 12% | E2: 1 | F2: 0 | G2: 0 | H2: 0
A3: 500 | B3: SAP | C3: 6046 | D3: DESAT CHAVE FUSIVEL 3 OP < 34,5 KV | E3: 0 | F3: 38.28 | G3: 0 | H3: 0
A4: 500 | B4: SAP | C4: 6071 | D4: INST CHAVE FUSIVEL < 34,5 KV LM | E4: 95.72 | F4: 0 | G4: 0 | H4: 0
A5: 500 | B5: SAP | C5: 6073 | D5: INST CHAVE FUSIVEL 3 OP < 34,5 KV | E5: 124.44 | F5: 0 | G5: 0 | H5: 0
A6: 500 | B6: SAP | C6: 6074 | D6: INST CHAVE FUSIVEL 3 OP => 34,5 KV | E6: 124.44 | F6: 0 | G6: 0 | H6: 0
A7: 500 | B7: SAP | C7: 6083 | D7: INST PARA-RAIOS RD => 34,5 KV LM | E7: 95.72 | F7: 0 | G7: 0 | H7: 0
A8: 500 | B8: SAP | C8: 6137 | D8: LIMP FAIXA SERVIDAO MECANIZADA | E8: 2758.72 | F8: 0 | G8: 0 | H8: 0
A9: 500 | B9: SAP | C9: 6220 | D9: INST CAIXA MED CPREDE 1 MEDID ELETROM LM | E9: 143.58 | F9: 0 | G9: 0 | H9: 0
A10: 500 | B10: SAP | C10: 6227 | D10: DESAT CX MED CP-REDE P/ 3 OU 4 MEDID LM | E10: 0 | F10: 191.44 | G10: 0 | H10: 0
A11: 500 | B11: SAP | C11: 6235 | D11: INST CONEC RD SEC LM | E11: 9.58 | F11: 0 | G11: 0 | H11: 0
A12: 500 | B12: SAP | C12: 6252 | D12: SERV AB/FEC VAL ATER EM TERRA | E12: 17.23 | F12: 0 | G12: 0 | H12: 0
A13: 500 | B13: SAP | C13: 6281 | D13: DESAT ESTAI ANCORA CHUMBADO ROCHA LM | E13: 0 | F13: 95.72 | G13: 0 | H13: 0
... A579: 124 | B579: LINHA VIVA - ESTRUTURAS COMPLETAS | C579: 8091 | D579: INST SUP P/TRANSF <69KV LM | E579: 38.28 | F579: 0 | G579: 0 | H579: 0
C580: 8771 | D580: DESAT CH TRIP OLEO ABER CARGA < 69 KV LV | E580: 0 | F580: 373.54
C581: 92324 | D581: HORA DO COLABORADOR EM DISPONIBILIDADE PARA OUTRA REGIONAL - LM_x000D_ | E581: 87.11 | F581: 0

Sheet PADRAO
B3: EQUIPE=> | D3: ENCARREGADO: | J3: DATA SAÍDA=> | S3: DATA RETORNO=> | X3: TÉCNICO ENG:
B5: ENDEREÇO=> | W5: NR
B7: ELETRICISTAS=>
B9: SAIDA BASE => | H9: RETORNO BASE => | P9: =L9-D9+12 -> 12 | S9: KM INICIAL=> | AC9: KM | AD9: ;
B11: INICIO SERVIÇO => | H11: RETORNO SERVIÇO => | P11: =L11-D11+12 -> 12 | S11: KM FINAL=>
B13: CÓD. ACIONAMENTO=> | H13: Nº INTERVENÇÃO=> | R13: NOTA (SS)=> | X13: OS TABLET =>
B15: OBSERVAÇÃO =>
B17: TRANSFORMADOR RETIRADO POTENCIA => | J17: MARCA => | Q17: FABRICAÇÃO =>
B18: TENSÃO SEGUNDARIA=> | G18: V | H18: TENSÃO PRIMARIA=> | N18: KV | P18: Nº SERIE => | W18: PATRIMONIO =>
B20: TRANSFORMADOR INSTALADO POTENCIA => | J20: MARCA => | Q20: FABRICAÇÃO =>
B21: TENSÃO SEGUNDARIA=> | G21: V | H21: TENSÃO PRIMARIA=> | N21: KV | P21: Nº SERIE => | W21: PATRIMONIO =>
B22: A-N=> | D22: B-N=> | H22: C-N=> | J22: A-B=> | M22: A-C=> | P22: B-C=> | T22: A=> | V22: B=> | X22: C=> | AA22: N=>
B24: ALIMENTADOR => | D24: 003 | H24: SUBESTAÇÃO => | J24: 011 | M24: Nº TRANSFORMADOR => | U24: Nº ID POSTE => | W24: 36590316
B26: ITEM | C26: CÓD | D26: MÃO DE OBRA | V26: Un | W26: R$ | X26: OPERAÇÕES
Y27: Inst. | Z27: Ret. | AA27: TOTAL | AB27: R$
B28: 1 | C28: 10521 | D28: =IF(C28="","",VLOOKUP(C28,'MÃO OBRA'!A$2:G$581,2,FALSE)) -> SERV INSPECAO EM REDE RURAL LM | V28: =IF(C28="","",VLOOKUP(C28,'MÃO OBRA'!A$2:F$581,3,FALSE)) -> UN | W28: =IF(C28="","",VLOOKUP(C28,'MÃO OBRA'!A$2:F$581,6,FALSE)) -> 32.55 | X28: 1 | AA28: =X28 -> 1 | AB28: =IF(C28="","",(W28*AA28)) -> 32.55
B29: 2 | D29: =IF(C29="","",VLOOKUP(C29,'MÃO OBRA'!A$2:G$581,2,FALSE)) | V29: =IF(C29="","",VLOOKUP(C29,'MÃO OBRA'!A$2:F$581,3,FALSE)) | W29: =IF(C29="","",VLOOKUP(C29,'MÃO OBRA'!A$2:F$581,6,FALSE)) | AA29: =X29 -> 0 | AB29: =IF(C29="","",(W29*AA29))
B30: 3 | D30: =IF(C30="","",VLOOKUP(C30,'MÃO OBRA'!A$2:G$581,2,FALSE)) | V30: =IF(C30="","",VLOOKUP(C30,'MÃO OBRA'!A$2:F$581,3,FALSE)) | W30: =IF(C30="","",VLOOKUP(C30,'MÃO OBRA'!A$2:F$581,6,FALSE)) | AA30: =X30 -> 0 | AB30: =IF(C30="","",(W30*AA30))
B31: 4 | D31: =IF(C31="","",VLOOKUP(C31,'MÃO OBRA'!A$2:G$581,2,FALSE)) | V31: =IF(C31="","",VLOOKUP(C31,'MÃO OBRA'!A$2:F$581,3,FALSE)) | W31: =IF(C31="","",VLOOKUP(C31,'MÃO OBRA'!A$2:F$581,6,FALSE)) | AA31: =X31 -> 0 | AB31: =IF(C31="","",(W31*AA31))
B32: 5 | D32: =IF(C32="","",VLOOKUP(C32,'MÃO OBRA'!A$2:G$581,2,FALSE)) | V32: =IF(C32="","",VLOOKUP(C32,'MÃO OBRA'!A$2:F$581,3,FALSE)) | W32: =IF(C32="","",VLOOKUP(C32,'MÃO OBRA'!A$2:F$581,6,FALSE)) | AA32: =X32 -> 0 | AB32: =IF(C32="","",(W32*AA32))
B33: 6 | D33: =IF(C33="","",VLOOKUP(C33,'MÃO OBRA'!A$2:G$581,2,FALSE)) | V33: =IF(C33="","",VLOOKUP(C33,'MÃO OBRA'!A$2:F$581,3,FALSE)) | W33: =IF(C33="","",VLOOKUP(C33,'MÃO OBRA'!A$2:F$581,6,FALSE)) | AA33: =X33 -> 0 | AB33: =IF(C33="","",(W33*AA33))
B34: 7 | D34: =IF(C34="","",VLOOKUP(C34,'MÃO OBRA'!A$2:G$581,2,FALSE)) | V34: =IF(C34="","",VLOOKUP(C34,'MÃO OBRA'!A$2:F$581,3,FALSE)) | W34: =IF(C34="","",VLOOKUP(C34,'MÃO OBRA'!A$2:F$581,6,FALSE)) | AA34: =X34 -> 0 | AB34: =IF(C34="","",(W34*AA34))
B35: 8 | D35: =IF(C35="","",VLOOKUP(C35,'MÃO OBRA'!A$2:G$581,2,FALSE)) | V35: =IF(C35="","",VLOOKUP(C35,'MÃO OBRA'!A$2:F$581,3,FALSE)) | W35: =IF(C35="","",VLOOKUP(C35,'MÃO OBRA'!A$2:F$581,6,FALSE)) | AA35: =X35 -> 0 | AB35: =IF(C35="","",(W35*AA35))
B36: 9 | D36: =IF(C36="","",VLOOKUP(C36,'MÃO OBRA'!A$2:G$581,2,FALSE)) | V36: =IF(C36="","",VLOOKUP(C36,'MÃO OBRA'!A$2:F$581,3,FALSE)) | W36: =IF(C36="","",VLOOKUP(C36,'MÃO OBRA'!A$2:F$581,6,FALSE)) | AA36: =X36 -> 0 | AB36: =IF(C36="","",(W36*AA36))
B37: 10 | D37: =IF(C37="","",VLOOKUP(C37,'MÃO OBRA'!A$2:G$581,2,FALSE)) | V37: =IF(C37="","",VLOOKUP(C37,'MÃO OBRA'!A$2:F$581,3,FALSE)) | W37: =IF(C37="","",VLOOKUP(C37,'MÃO OBRA'!A$2:F$581,6,FALSE)) | AA37: =X37 -> 0 | AB37: =IF(C37="","",(W37*AA37))
B38: 11 | D38: =IF(C38="","",VLOOKUP(C38,'MÃO OBRA'!A$2:G$581,2,FALSE)) | V38: =IF(C38="","",VLOOKUP(C38,'MÃO OBRA'!A$2:F$581,3,FALSE)) | W38: =IF(C38="","",VLOOKUP(C38,'MÃO OBRA'!A$2:F$581,6,FALSE)) | AA38: =X38 -> 0 | AB38: =IF(C38="","",(W38*AA38))
B39: 12 | D39: =IF(C39="","",VLOOKUP(C39,'MÃO OBRA'!A$2:G$581,2,FALSE)) | V39: =IF(C39="","",VLOOKUP(C39,'MÃO OBRA'!A$2:F$581,3,FALSE)) | W39: =IF(C39="","",VLOOKUP(C39,'MÃO OBRA'!A$2:F$581,6,FALSE)) | AA39: =X39 -> 0 | AB39: =IF(C39="","",(W39*AA39))
B40: 13 | D40: =IF(C40="","",VLOOKUP(C40,'MÃO OBRA'!A$2:G$581,2,FALSE)) | V40: =IF(C40="","",VLOOKUP(C40,'MÃO OBRA'!A$2:F$581,3,FALSE)) | W40: =IF(C40="","",VLOOKUP(C40,'MÃO OBRA'!A$2:F$581,6,FALSE)) | AA40: =X40 -> 0 | AB40: =IF(C40="","",(W40*AA40))
B41: 14 | D41: =IF(C41="","",VLOOKUP(C41,'MÃO OBRA'!A$2:G$581,2,FALSE)) | V41: =IF(C41="","",VLOOKUP(C41,'MÃO OBRA'!A$2:F$581,3,FALSE)) | W41: =IF(C41="","",VLOOKUP(C41,'MÃO OBRA'!A$2:F$581,6,FALSE)) | AA41: =X41 -> 0 | AB41: =IF(C41="","",(W41*AA41))
AB42: =SUM(AB28:AC41) -> 32.55
W43: =IF(X43>0,(243.02),"")
B44: 26376 | D44: SERV. EMERG. FORA DO HORARIO COMERCIAL-ADICIONAL 30% | V44: ADIC | W44: =IF(X44>0,(AB42*0.3),"0") -> 0 | AB44: =X44*W44 -> 0
B45: 92525 | D45: SERV. EMERG. HORARIO COMERCIAL - ADICIONAL 12% | V45: ADIC | W45: =IF(X45>0,(AB42*0.12),"0") -> 3.906 | X45: 1 | AB45: =X45*W45 -> 3.906
B46: 0 | AB46: =SUM(AB42:AC45) -> 36.456
B47: ITEM | C47: CÓD | D47: MATERIAL APLICADO | W47: UN | X47: OPERAÇÕES
Z48: =Z27 -> Ret. | AA48: TOTAL
B49: 1 | D49: =IF(C49="","",VLOOKUP(C49,MATERIAL!A:C,2,FALSE)) | W49: =IF(C49="","",VLOOKUP(C49,MATERIAL!A$3:C$528,3,FALSE)) | AA49: =SUM(X49:Z49) -> 0 | AB49: =IF(C49="","",(X49))
B50: 2 | D50: =IF(C50="","",VLOOKUP(C50,MATERIAL!A:C,2,FALSE)) | W50: =IF(C50="","",VLOOKUP(C50,MATERIAL!A$3:C$528,3,FALSE)) | AA50: =SUM(X50:Z50) -> 0 | AB50: =IF(C50="","",(X50))
B51: 3 | D51: =IF(C51="","",VLOOKUP(C51,MATERIAL!A:C,2,FALSE)) | W51: =IF(C51="","",VLOOKUP(C51,MATERIAL!A$3:C$528,3,FALSE)) | AA51: =SUM(X51:Z51) -> 0 | AB51: =IF(C51="","",(X51))
B52: 4 | D52: =IF(C52="","",VLOOKUP(C52,MATERIAL!A:C,2,FALSE)) | W52: =IF(C52="","",VLOOKUP(C52,MATERIAL!A$3:C$528,3,FALSE)) | AA52: =SUM(X52:Z52) -> 0 | AB52: =IF(C52="","",(X52))
B53: 5 | D53: =IF(C53="","",VLOOKUP(C53,MATERIAL!A:C,2,FALSE)) | W53: =IF(C53="","",VLOOKUP(C53,MATERIAL!A$3:C$528,3,FALSE)) | AA53: =SUM(X53:Z53) -> 0 | AB53: =IF(C53="","",(X53))
B54: ITEM | C54: CÓD | D54: MATERIAL RETIRADO | W54: UN | X54: OPERAÇÕES | AC54: TOTAL
X55: SUCATA | Y55: REFORMA | AA55: BOM | AB55: DESCARTE
B56: 1 | D56: =IF(C56="","",VLOOKUP(C56,MATERIAL!A:C,2,FALSE)) | W56: =IF(C56="","",VLOOKUP(C56,MATERIAL!A$3:C$528,3,FALSE)) | AC56: =SUM(X56:AB56) -> 0
B57: 2 | D57: =IF(C57="","",VLOOKUP(C57,MATERIAL!A:C,2,FALSE)) | W57: =IF(C57="","",VLOOKUP(C57,MATERIAL!A$3:C$528,3,FALSE)) | AC57: =SUM(X57:AB57) -> 0
B58: 3 | D58: =IF(C58="","",VLOOKUP(C58,MATERIAL!A:C,2,FALSE)) | W58: =IF(C58="","",VLOOKUP(C58,MATERIAL!A$3:C$528,3,FALSE)) | AC58: =SUM(X58:AB58) -> 0
B59: 4 | D59: =IF(C59="","",VLOOKUP(C59,MATERIAL!A:C,2,FALSE)) | W59: =IF(C59="","",VLOOKUP(C59,MATERIAL!A$3:C$528,3,FALSE)) | AC59: =SUM(X59:AB59) -> 0
B60: 5 | D60: =IF(C60="","",VLOOKUP(C60,MATERIAL!A:C,2,FALSE)) | W60: =IF(C60="","",VLOOKUP(C60,MATERIAL!A$3:C$528,3,FALSE)) | AC60: =SUM(X60:AB60) -> 0

Sheet MÃO OBRA
A1: CÓDIGOS SIAGO | B1: DESCRIÇÃO BÁSICA | C1: U N | D1: VALOR | E1: T/H | F1: VALOR R$ 2021 | G1: Nº CONTRATO | H1: Inst. | I1: Ret.
A2: 4595 | B2: Alteração de US - Item a ser utilizado para pagamento da diferença na medição de mão de obra quando houver ajuste no valor da US. | C2: UN | E2: 0.20006858 | F2: 1 | G2: 2024014901 | H2: x
A3: 6042 | B3: DESAT CHAVE FUSIVEL < 34,5 KV LM | C3: UN | E3: 2.9900566 | F3: 28.72 | G3: 2024014901 | H3: x
A4: 6043 | B4: DESAT CHAVE FUSIVEL => 34,5 KV LM | F4: 28.72 | G4: 2024014901
A5: 6046 | B5: DESAT CHAVE FUSIVEL 3 OP < 34,5 KV | C5: UN | D5: 9.74 | E5: 12 | F5: 38.28 | G5: 2021014001 | H5: x
A6: 6047 | B6: DESAT CHAVE FUSIVEL 3 OP => 34,5 KV | C6: UN | D6: 48.71 | E6: 7.5000857 | F6: 38.28 | G6: 2024014901 | H6: x
A7: 6055 | B7: DESAT PARA-RAIOS RD < 34,5 KV LM | F7: 28.72 | G7: 2024014901
A8: 6056 | B8: DESAT TRANSF DIST AEREO MONOFASICO LM | C8: UN | D8: 162.36 | E8: 1 | F8: 191.44 | G8: 2024014901 | H8: x
A9: 6061 | B9: DESAT TRANSF DISTRIBUIC AEREO 3F LM | F9: 287.17 | G9: 2024014901
A10: 6062 | B10: DESATIVAR CHAVE SECC FACA => 15 KV LM | F10: 28.72 | G10: 2024014901
A11: 6069 | B11: INST CH SECC S/LAM TER MONO MAN <69KV | F11: 95.72 | G11: 2024014901
A12: 6071 | B12: INST CHAVE FUSIVEL < 34,5 KV LM | C12: UN | E12: 7.1500086 | F12: 95.72 | G12: 2021014001 | H12: x
A13: 6072 | B13: INST CHAVE FUSIVEL => 34,5KV LM | C13: UN | D13: 162.36 | E13: 1.9699983 | F13: 95.72 | G13: 2024014901 | H13: x | I13: x
A14: 6073 | B14: INST CHAVE FUSIVEL 3 OP < 34,5 KV | C14: UN | E14: 66 | F14: 124.44 | G14: 2021014001 | H14: x
A15: 6074 | B15: INST CHAVE FUSIVEL 3 OP => 34,5 KV | C15: UN | D15: 97.42 | E15: 1.5000857 | F15: 124.44 | G15: 2021014001 | H15: x
A16: 6082 | B16: INST PARA-RAIOS RD < 34,5 KV LM | C16: UN | D16: 185.09 | E16: 54.669981 | F16: 95.72 | G16: 2024014901 | H16: x
A17: 6083 | B17: INST PARA-RAIOS RD => 34,5 KV LM | C17: UN | D17: 73.06 | E17: 4 | F17: 95.72 | G17: 2021014001 | H17: x
A18: 6092 | B18: INST TRANSF DISTRIBUIC AEREO MONO LM | C18: UN | D18: 974.16 | E18: 46 | F18: 765.78 | G18: 2024014901 | H18: x
A19: 6093 | B19: INST TRANSF DISTRIBUIC AEREO TRIF LM | C19: UN | E19: 56 | F19: 1052.94 | G19: 2024014901 | H19: x
A20: 6102 | B20: SUBST PARA-RAIO RD <34,5KV LV | C20: UN | D20: 2435.4 | E20: 2 | F20: 166.37 | G20: 2024014901 | I20: x
A21: 6128 | B21: LIMP FAIXA CERRADO E CAPOEIRA | C21: UN | D21: 243.54 | E21: 26.599863 | F21: 1544 | G21: 2024014901 | H21: x | I21: x
A22: 6129 | B22: LIMP FAIXA VEGETACAO DENSA | C22: UN | E22: 2 | F22: 2105.89 | G22: 2024014901 | I22: x
A23: 6133 | B23: DISP H-MAQ P/EXEC SERV LM | C23: UN | D23: 2435.4 | E23: 0.50008572 | F23: 974.45 | G23: 2024014901 | I23: x
A24: 6137 | B24: LIMP FAIXA SERVIDAO MECANIZADA | C24: UN | E24: 14.200069 | F24: 2758.72 | G24: 2021014001 | H24: x
A25: 6151 | B25: DESLOC EQUIP PESADA ACIMA 50 KM DA BASE | F25: 5.75 | G25: 2024014901
A26: 6155 | B26: SERV OFIC PODAR ARVORE RURAL LM | F26: 67 | G26: 2024014901
A27: 6156 | B27: PODAR ARV GRANDE LM | F27: 67 | G27: 2024014901
A28: 6169 | B28: LIMP FAIXA CAMPO-10M LARGURA | F28: 1052.94 | G28: 2024014901
A29: 6170 | B29: OPER CHAVE FACA AB E FC EMERG LM | C29: UN | D29: 77.93 | E29: 0.18001029 | F29: 47.86 | G29: 2024014901 | H29: x
A30: 6171 | B30: OPER CHAVE FUS AB E FC EMERG LM | C30: UN | D30: 73.06 | E30: 28 | F30: 47.86 | G30: 2024014901 | H30: x
A31: 6181 | B31: SERVIÇO EXCLUSIVO DE PODA DE ARVORE URB/RUR C/RECOLHA | C31: UN | E31: 0.27995885 | F31: 69.88 | G31: 2024014901 | H31: x | I31: x
A32: 6182 | B32: SERVIÇO EXCLUSIVO DE PODA DE ARVORE URB/RUR S/RECOLHA | C32: UN | D32: 64.94 | E32: 0.50008572 | F32: 47.86 | G32: 2024014901 | I32: x
A33: 6195 | B33: INST MED MEDIA TENSAO CONJ TCS E TPS | F33: 1052.94 | G33: 2024014901
A34: 6196 | B34: INST PADR ENERG TRIF T5/T6/T7-INDIR LM | C34: UN | E34: 0.50008572 | F34: 1531.56 | G34: 2024014901 | I34: x
A35: 6210 | B35: EFET RECUPER CX CP REDE LM | C35: UN | D35: 232.17 | E35: 0.50008572 | F35: 7.66 | G35: 2024014901 | I35: x
A36: 6212 | B36: DESAT MED EM CAIXA CP-REDE BIFASICO LM | F36: 81.36 | G36: 2024014901
A37: 6213 | B37: DESAT MED EM CAIXA CP-REDE TRIFASICO LM | C37: UN | D37: 211.07 | E37: 0.50008572 | F37: 119.66 | G37: 2024014901 | I37: x
A38: 6216 | B38: INS RAMAL ENTR C/ELETR CX CP RD LM | C38: UN | D38: 405.9 | E38: 2.9900566 | F38: 114.86 | G38: 2024014901 | H38: x
A39: 6217 | B39: DESAT MED EM CAIXA CP-TRAFO LM | C39: UN | E39: 0.54997428 | F39: 105.3 | G39: 2024014901 | H39: x | I39: x
A40: 6220 | B40: INST CAIXA MED CPREDE 1 MEDID ELETROM LM | C40: UN | E40: 2 | F40: 143.58 | G40: 2021014001 | H40: x
A41: 6221 | B41: INST CAIXA MED CP-REDE CONEX/RAMAIS LM | C41: UN | D41: 1298.88 | E41: 0.50008572 | F41: 339.81 | G41: 2024014901 | I41: x
A42: 6223 | B42: CODIF EQUIP DISTRIBUICAO LM | C42: UN | D42: 81.18 | E42: 0.33996228 | F42: 9.58 | G42: 2024014901 | H42: x
A43: 6224 | B43: ABRIR CAVA EM TERRA NORMAL | C43: UN | E43: 2 | F43: 143.58 | G43: 2024014901 | H43: x
A44: 6225 | B44: CONFECC BASE CONC SIMPLES | C44: UN | D44: 162.36 | E44: 0.159952 | F44: 1340.11 | G44: 2024014901 | I44: x
A45: 6226 | B45: DESAT CX MED CP-REDE CONEX RAMAI UC LM | C45: UN | E45: 1 | F45: 223.03 | G45: 2024014901 | H45: x
A46: 6227 | B46: DESAT CX MED CP-REDE P/ 3 OU 4 MEDID LM | C46: UN | E46: 0.099948568 | F46: 191.44 | G46: 2021014001 | H46: x
A47: 6228 | B47: DESAT CX MED CP-REDE P/1 MEDIDOR LM | C47: UN | D47: 324.72 | E47: 2 | F47: 95.72 | G47: 2024014901 | H47: x
A48: 6229 | B48: DESAT CX MED CP-REDE P/6 OU 8 MEDID LM | F48: 382.89 | G48: 2024014901
A49: 6230 | B49: DESAT POSTE ATE 13 <69KV GUIND LM | C49: UN | D49: 649.44 | E49: 1 | F49: 287.17 | G49: 2024014901 | H49: x
A50: 6233 | B50: INST CINTA CX CP REDE PST LM | C50: UN | E50: 0.50008572 | F50: 47.86 | G50: 2024014901 | I50: x
A51: 6234 | B51: INST CONEC RD PRIM LM | C51: UN | D51: 211.07 | E51: 1 | F51: 19.14 | G51: 2024014901 | H51: x
A52: 6235 | B52: INST CONEC RD SEC LM | C52: UN | D52: 16.24 | E52: 14 | F52: 9.58 | G52: 2021014001 | H52: x
A53: 6239 | B53: INST MED EM CAIXA CP-TRAFO LM | C53: UN | D53: 276.01 | E53: 16 | F53: 239.31 | G53: 2024014901 | H53: x
A54: 6240 | B54: INST PADR ENERG MONOFASICO LM | C54: UN | E54: 1.8899366 | F54: 191.44 | G54: 2024014901 | H54: x | I54: x
A55: 6241 | B55: INST ATER POR HASTE LM | C55: UN | D55: 128.26 | E55: 1 | F55: 47.86 | G55: 2024014901 | I55: x
A56: 6242 | B56: INST PADR ENERG TRIFASICO LM | F56: 191.44 | G56: 2024014901
A57: 6243 | B57: INST POSTE ATE 13M <69KV GUIN LM | C57: UN | D57: 324.72 | E57: 0.18995371 | F57: 287.17 | G57: 2024014901 | I57: x
A58: 6244 | B58: INST ESTRIBO REDE MT LM | C58: UN | E58: 1 | F58: 19.14 | G58: 2024014901 | H58: x
A59: 6245 | B59: REMAN PST C/USO GUIND LM | F59: 574.33 | G59: 2024014901
A60: 6246 | B60: NIVELAR COND RAMAL SERV LM | C60: UN | E60: 1.3000171 | F60: 47.86 | G60: 2024014901 | H60: x
A61: 6247 | B61: EST ILUM INST LUMIN SIMPLES LM | C61: UN | E61: 0.20006858 | F61: 239.31 | G61: 2024014901 | I61: x
A62: 6249 | B62: DESAT MED EM CAIXA CP-REDE MONOFAS LM | C62: UN | E62: 1.3000171 | F62: 67 | G62: 2024014901 | H62: x
A63: 6250 | B63: INST RAMAL SERVICO MONOFASICO LM | C63: UN | D63: 45.46 | E63: 2 | F63: 47.86 | G63: 2024014901 | H63: x
A64: 6252 | B64: SERV AB/FEC VAL ATER EM TERRA | C64: UN | E64: 2.5000857 | F64: 17.23 | G64: 2021014001 | H64: x
A65: 6253 | B65: INST RAMAL SERVICO BIFASICO LM | F65: 47.86 | G65: 2024014901
A66: 6254 | B66: INST RAMAL SERVICO TRIFASICO LM | F66: 47.86 | G66: 2024014901
A67: 6255 | B67: EFET MAN CX CP REDE LM | F67: 124.44 | G67: 2024014901
A68: 6280 | B68: DESAT CRUZETA SIMPLES LM | C68: UN | E68: 0.50008572 | F68: 95.72 | G68: 2024014901 | H68: x
A69: 6281 | B69: DESAT ESTAI ANCORA CHUMBADO ROCHA LM | C69: UN | E69: 3 | F69: 95.72 | G69: 2021014001 | H69: x
A70: 6284 | B70: DESAT EST PRIM N3/N3-E/M3/B3/B3-E LM | C70: UN | E70: 1.5000857 | F70: 191.44 | G70: 2024014901 | H70: x
A71: 6285 | B71: DESAT EST PRIM N3-2/M3-2/N2-3/M2-3 LM | C71: UN | E71: 0.84999143 | F71: 191.44 | G71: 2024014901 | I71: x
A72: 6286 | B72: DESAT EST PRIM N3-N3/M3-M3 LM | C72: UN | E72: 1 | F72: 191.44 | G72: 2024014901 | H72: x
A73: 6287 | B73: DESAT EST PRI N4/N4E/M4/B4/B4E C/CHAV LM | F73: 191.44 | G73: 2024014901
A74: 6288 | B74: RET OBJ ESTRANHO REDE LM | F74: 28.72 | G74: 2024014901
A75: 6289 | B75: DESAT POSTE ACIMA 13 LM | C75: UN | D75: 58.45 | E75: 1 | F75: 430.75 | G75: 2024014901 | H75: x
A76: 6290 | B76: DESAT REGUL NA REDE MT LM | C76: KM | E76: 0.69998286 | F76: 287.17 | G76: 2024014901 | I76: x
A77: 6291 | B77: DESAT RELIGADOR NA REDE MT LM | F77: 287.17 | G77: 2024014901
A78: 6294 | B78: ABER-FECH VALETA RECOM PISO CALCADA LM | C78: UN | D78: 138.01 | E78: 1 | F78: 47.86 | G78: 2024014901 | H78: x
A79: 6295 | B79: REEMB ATEST ALINH POR PST LM | F79: 9.58 | G79: 2024014901
A80: 6296 | B80: DESAT RAMAL SERVICO BIFASICO LM | F80: 19.14 | G80: 2024014901
A81: 6297 | B81: DESAT RAMAL SERVICO MONOFASICO LM | F81: 19.14 | G81: 2024014901
A82: 6298 | B82: DESAT RAMAL SERVICO TRIFASICO LM | C82: UN | D82: 162.36 | E82: 2 | F82: 19.14 | G82: 2021014001 | I82: x
A83: 6299 | B83: INSPEC POST TRAN RUR LM | C83: UN | E83: 0.022972741 | F83: 86.15 | G83: 2024014901 | H83: x
A84: 6309 | B84: INST PARA-RAIOS RD <34,5 KV LM | C84: UN | E84: 2.2799589 | F84: 95.72 | G84: 2024014901 | H84: x | I84: x
A85: 6311 | B85: INST ISOLADOR DISCO LM | C85: UN | E85: 2 | F85: 47.86 | G85: 2024014901 | H85: x
A86: 6315 | B86: INST SERV TEC COM BALANC CARGA REDE BT | F86: 47.86 | G86: 2024014901
A87: 6316 | B87: CONFECC BASE CONC TOTAL / SOLO CIMENTO | F87: 239.31 | G87: 2024014901
A88: 6317 | B88: DISTR PST RUR LM | C88: UN | E88: 0.050060003 | F88: 287.17 | G88: 2021014001 | I88: x
A89: 6318 | B89: EMEND COND PRIM PROTEG LM | C89: UN | E89: 2.2799589 | F89: 95.72 | G89: 2024014901 | H89: x | I89: x
A90: 6319 | B90: INST EMENDA COND PRIM/SEC NU LM | C90: UN | E90: 0.69998286 | F90: 57.44 | G90: 2024014901 | H90: x
A91: 6322 | B91: INST BANCO CAPACITOR 900KVAR LM | C91: UN | D91: 162.36 | E91: 0.20006858 | F91: 1194.61 | G91: 2024014901 | H91: x
A92: 6325 | B92: INST ESTRUTURA PRIM HS LM | C92: UN | D92: 2273.04 | E92: 0.060003429 | F92: 478.61 | G92: 2021014001 | I92: x
A93: 6327 | B93: INST ESTR PRIM N3-N3/M3-M3 LM | F93: 478.61 | G93: 2024014901
A94: 6329 | B94: INST POSTO TRANSF ESTRUT MT1 LM | C94: UN | E94: 0.93999657 | F94: 2105.89 | G94: 2024014901 | H94: x | I94: x
A95: 6330 | B95: INST POSTO TRANSF ESTRUT MT2 LM | C95: UN | E95: 2.0200583 | F95: 2393.06 | G95: 2024014901 | H95: x | I95: x
A96: 6332 | B96: INST SAPATA PANTANO COM MANILHA | C96: UN | D96: 58.45 | E96: 3 | F96: 1435.83 | G96: 2021014001 | I96: x
A97: 6333 | B97: LANCAR COND ELETR SUBTER LM | C97: UN | E97: 60 | F97: 4.78 | G97: 2024014901 | H97: x
A98: 6335 | B98: PINTAR Nº PATR EQU INST LM | C98: UN | E98: 10.480027 | F98: 47.86 | G98: 2024014901 | H98: x | I98: x
A99: 6336 | B99: REINST POSTE ACIMA DE 13M LM | C99: UN | D99: 193.21 | E99: 1.2499571 | F99: 604.01 | G99: 2024014901 | I99: x
A100: 6338 | B100: REINST POSTE DE 8,5 ATE 13M LM | C100: UN | D100: 193.21 | E100: 4.5000857 | F100: 409.99 | G100: 2024014901 | H100: x
...

Sheet FECHAMENTO
M1: =SUM(N4:N688) -> 0
A3: LOTE ENVIADO | B3: DATA ENVIO LOTE | C3: Nº CONTRATO | D3: DATA EXECUÇÃO | E3: EQUIPE | F3: ENCARREGADO | G3: IDENTIFICAÇÃO EQUIPAMENTO | H3: OS COI | I3: OS PRIMARIA | J3: OS SECUNDARIA | K3: CONTROLE CRS | L3: Apoio Linha Viva | M3: Nº DA OBRA EMERGENCIAL | N3: VALOR CRS | O3: VALOR NÚCLEO | P3: DIFERENÇA | Q3: OBSERVAÇÕES ENERGISA | R3: OBSERVAÇÕES DINAMO

Sheet Obras
A1: LOTE ENVIADO | B1: DATA ENVIO LOTE | C1: Nº CONTRATO | D1: DATA EXECUÇÃO | E1: EQUIPE | F1: ENCARREGADO | G1: IDENTIFICAÇÃO EQUIPAMENTO | H1: OS COI | I1: OS PRIMARIA | J1: OS SECUNDARIA | K1: CONTROLE CRS | L1: Apoio Linha Viva | M1: Nº DA OBRA EMERGENCIAL | N1: VALOR CRS | O1: VALOR NÚCLEO | P1: DIFERENÇA | Q1: OBSERVAÇÕES ENERGISA | R1: OBSERVAÇÕES DINAMO

Sheet 5716677005
A2: EQUIPE=> | B2: 96 | C2: ENCARREGADO: | G2: ELIEZER | I2: DATA SAÍDA=> | L2: Segunda-feira, 2 de maio de 2022 | R2: DATA RETORNO=> | S2: Segunda-feira, 2 de maio de 2022 | W2: TÉCNICO DIN: | Z2: ARINEY
A4: ENDEREÇO=> | C4: Rua Radialista Reinaldo Veiga, 8 - Coophamil, Cuiabá - MT, 78028-180 | V4: NR | X4: DINEM20220***
A6: ELETRICISTAS=> | C6: JOILSON / RONILSON
A8: SAIDA BASE => | C8: 08:35 | G8: RETORNO BASE => | K8: 0.73958333 | O8: =K8-C8 -> 0.38194444 | R8: KM INICIAL=> | T8: 59600 | V8: =T10-T8 -> 30 | AB8: KM
A10: INICIO SERVIÇO => | C10: 10:45 | G10: RETORNO SERVIÇO => | K10: 0.68055556 | O10: =K10-C10 -> 0.23263889 | R10: KM FINAL=> | T10: 59630
A12: CÓD. ACIONAMENTO=> | G12: Nº INTERVENÇÃO=> | J12: 20222986520197 | Q12: NOTA (SS)=> | S12: EMT-RD-ME002901/2022 | W12: OS TABLET =>
A14: OBSERVAÇÃO =>
A16: TRANSFORMADOR RETIRADO POTENCIA => | G16: 75 KVA | I16: MARCA => | L16: WEG | P16: FABRICAÇÃO => | R16: 12 / 1990
A17: TENSÃO SEGUNDARIA=> | C17: 127/220 | F17: V | G17: TENSÃO PRIMARIA=> | J17: 44786 | M17: KV | O17: Nº SERIE => | R17: 73799 | V17: PATRIMONIO => | Y17: N/A
A19: TRANSFORMADOR INSTALADO POTENCIA => | G19: 112,5 KVA | I19: MARCA => | L19: ITAIPU | P19: FABRICAÇÃO => | R19: 02 / 2022
A20: TENSÃO SEGUNDARIA=> | C20: 127/220 | F20: V | G20: TENSÃO PRIMARIA=> | J20: 44786 | M20: KV | O20: Nº SERIE => | R20: 452882 | V20: PATRIMONIO => | Y20: 275400
A21: A-N=> | B21: 120 | C21: B-N=> | E21: 122 | G21: C-N=> | H21: 126 | I21: A-B=> | K21: 225 | L21: A-C=> | M21: 215 | O21: B-C=> | Q21: 218 | S21: A=> | T21: 38 | U21: B=> | V21: 20 | W21: C=> | X21: 38 | Z21: N=> | AA21: 16
A23: ALIMENTADOR => | G23: SUBESTAÇÃO => | L23: Nº TRANSFORMADOR => | Q23: 5716677005 | T23: Nº ID POSTE =>
A25: ITEM | B25: CÓD | U25: Un | V25: R$ | W25: OPERAÇÕES
X26: Inst. | Y26: Ret. | Z26: TOTAL | AA26: R$
A27: 1 | B27: 6061 | C27: =IF(B27="","",VLOOKUP(B27,'MÃO OBRA'!A$2:G$436,2,FALSE)) -> DESAT TRANSF DISTRIBUIC AEREO 3F LM | U27: =IF(B27="","",VLOOKUP(B27,'MÃO OBRA'!A$2:F$35064,3,FALSE)) -> 0 | V27: =IF(B27="","",VLOOKUP(B27,'MÃO OBRA'!A$2:F$21664,6,FALSE)) -> 287.17 | W27: 1 | X27: =IFERROR(VLOOKUP(B27,'MÃO OBRA'!A:H,8,FALSE),"") -> 0 | Y27: =IFERROR(VLOOKUP(B27,'MÃO OBRA'!A:I,9,FALSE),"") -> 0 | Z27: =W27 -> 1 | AA27: =IF(B27="","",(V27*Z27)) -> 287.17
A28: =A27+1 -> 2 | B28: 6093 | C28: =IF(B28="","",VLOOKUP(B28,'MÃO OBRA'!A$2:G$436,2,FALSE)) -> INST TRANSF DISTRIBUIC AEREO TRIF LM | U28: =IF(B28="","",VLOOKUP(B28,'MÃO OBRA'!A$2:F$35064,3,FALSE)) -> UN | V28: =IF(B28="","",VLOOKUP(B28,'MÃO OBRA'!A$2:F$21664,6,FALSE)) -> 1052.94 | W28: 1 | X28: =IFERROR(VLOOKUP(B28,'MÃO OBRA'!A:H,8,FALSE),"") -> x | Y28: =IFERROR(VLOOKUP(B28,'MÃO OBRA'!A:I,9,FALSE),"") -> 0 | Z28: =W28 -> 1 | AA28: =IF(B28="","",(V28*Z28)) -> 1052.94
A29: =A28+1 -> 3 | B29: 7038 | C29: =IF(B29="","",VLOOKUP(B29,'MÃO OBRA'!A$2:G$436,2,FALSE)) -> #N/A | U29: =IF(B29="","",VLOOKUP(B29,'MÃO OBRA'!A$2:F$35064,3,FALSE)) -> UN | V29: =IF(B29="","",VLOOKUP(B29,'MÃO OBRA'!A$2:F$21664,6,FALSE)) -> 124.44 | W29: 1 | X29: =IFERROR(VLOOKUP(B29,'MÃO OBRA'!A:H,8,FALSE),"") -> 0 | Y29: =IFERROR(VLOOKUP(B29,'MÃO OBRA'!A:I,9,FALSE),"") -> x | Z29: =W29 -> 1 | AA29: =IF(B29="","",(V29*Z29)) -> 124.44
A30: =A29+1 -> 4 | B30: 6171 | C30: =IF(B30="","",VLOOKUP(B30,'MÃO OBRA'!A$2:G$436,2,FALSE)) -> OPER CHAVE FUS AB E FC EMERG LM | U30: =IF(B30="","",VLOOKUP(B30,'MÃO OBRA'!A$2:F$35064,3,FALSE)) -> UN | V30: =IF(B30="","",VLOOKUP(B30,'MÃO OBRA'!A$2:F$21664,6,FALSE)) -> 47.86 | W30: 3 | X30: =IFERROR(VLOOKUP(B30,'MÃO OBRA'!A:H,8,FALSE),"") -> x | Y30: =IFERROR(VLOOKUP(B30,'MÃO OBRA'!A:I,9,FALSE),"") -> 0 | Z30: =W30 -> 3 | AA30: =IF(B30="","",(V30*Z30)) -> 143.58
A31: =A30+1 -> 5 | B31: 6501 | C31: =IF(B31="","",VLOOKUP(B31,'MÃO OBRA'!A$2:G$436,2,FALSE)) -> SUBST ELO FUSIVEL LM | U31: =IF(B31="","",VLOOKUP(B31,'MÃO OBRA'!A$2:F$35064,3,FALSE)) -> 0 | V31: =IF(B31="","",VLOOKUP(B31,'MÃO OBRA'!A$2:F$21664,6,FALSE)) -> 47.86 | W31: 3 | X31: =IFERROR(VLOOKUP(B31,'MÃO OBRA'!A:H,8,FALSE),"") -> 0 | Y31: =IFERROR(VLOOKUP(B31,'MÃO OBRA'!A:I,9,FALSE),"") -> 0 | Z31: =W31 -> 3 | AA31: =IF(B31="","",(V31*Z31)) -> 143.58
A32: 6 | B32: 6082 | C32: =IF(B32="","",VLOOKUP(B32,'MÃO OBRA'!A$2:G$436,2,FALSE)) -> INST PARA-RAIOS RD < 34,5 KV LM | U32: =IF(B32="","",VLOOKUP(B32,'MÃO OBRA'!A$2:F$35064,3,FALSE)) -> UN | V32: =IF(B32="","",VLOOKUP(B32,'MÃO OBRA'!A$2:F$21664,6,FALSE)) -> 95.72 | W32: 3 | X32: =IFERROR(VLOOKUP(B32,'MÃO OBRA'!A:H,8,FALSE),"") -> x | Y32: =IFERROR(VLOOKUP(B32,'MÃO OBRA'!A:I,9,FALSE),"") -> 0 | Z32: =W32 -> 3 | AA32: =IF(B32="","",(V32*Z32)) -> 287.16
A33: =A32+1 -> 7 | B33: 6083 | C33: =IF(B33="","",VLOOKUP(B33,'MÃO OBRA'!A$2:G$436,2,FALSE)) -> INST PARA-RAIOS RD => 34,5 KV LM | U33: =IF(B33="","",VLOOKUP(B33,'MÃO OBRA'!A$2:F$35064,3,FALSE)) -> UN | V33: =IF(B33="","",VLOOKUP(B33,'MÃO OBRA'!A$2:F$21664,6,FALSE)) -> 95.72 | W33: 3 | X33: =IFERROR(VLOOKUP(B33,'MÃO OBRA'!A:H,8,FALSE),"") -> x | Y33: =IFERROR(VLOOKUP(B33,'MÃO OBRA'!A:I,9,FALSE),"") -> 0 | Z33: =W33 -> 3 | AA33: =IF(B33="","",(V33*Z33)) -> 287.16
A34: =A33+1 -> 8 | B34: 6235 | C34: =IF(B34="","",VLOOKUP(B34,'MÃO OBRA'!A$2:G$436,2,FALSE)) -> INST CONEC RD SEC LM | U34: =IF(B34="","",VLOOKUP(B34,'MÃO OBRA'!A$2:F$35064,3,FALSE)) -> UN | V34: =IF(B34="","",VLOOKUP(B34,'MÃO OBRA'!A$2:F$21664,6,FALSE)) -> 9.58 | W34: 8 | X34: =IFERROR(VLOOKUP(B34,'MÃO OBRA'!A:H,8,FALSE),"") -> x | Y34: =IFERROR(VLOOKUP(B34,'MÃO OBRA'!A:I,9,FALSE),"") -> 0 | Z34: =W34 -> 8 | AA34: =IF(B34="","",(V34*Z34)) -> 76.64
A35: =A34+1 -> 9 | B35: 6055 | C35: =IF(B35="","",VLOOKUP(B35,'MÃO OBRA'!A$2:G$436,2,FALSE)) -> DESAT PARA-RAIOS RD < 34,5 KV LM | U35: =IF(B35="","",VLOOKUP(B35,'MÃO OBRA'!A$2:F$35064,3,FALSE)) -> 0 | V35: =IF(B35="","",VLOOKUP(B35,'MÃO OBRA'!A$2:F$21664,6,FALSE)) -> 28.72 | W35: 3 | X35: =IFERROR(VLOOKUP(B35,'MÃO OBRA'!A:H,8,FALSE),"") -> 0 | Y35: =IFERROR(VLOOKUP(B35,'MÃO OBRA'!A:I,9,FALSE),"") -> 0 | Z35: =W35 -> 3 | AA35: =IF(B35="","",(V35*Z35)) -> 86.16
A36: =A35+1 -> 10 | B36: 7640 | C36: =IF(B36="","",VLOOKUP(B36,'MÃO OBRA'!A$2:G$436,2,FALSE)) -> #N/A | U36: =IF(B36="","",VLOOKUP(B36,'MÃO OBRA'!A$2:F$35064,3,FALSE)) -> 0 | V36: =IF(B36="","",VLOOKUP(B36,'MÃO OBRA'!A$2:F$21664,6,FALSE)) -> 19.14 | W36: 8 | X36: =IFERROR(VLOOKUP(B36,'MÃO OBRA'!A:H,8,FALSE),"") -> 0 | Y36: =IFERROR(VLOOKUP(B36,'MÃO OBRA'!A:I,9,FALSE),"") -> 0 | Z36: =W36 -> 8 | AA36: =IF(B36="","",(V36*Z36)) -> 153.12
A37: =A36+1 -> 11 | C37: =IF(B37="","",VLOOKUP(B37,'MÃO OBRA'!A$2:G$436,2,FALSE)) | U37: =IF(B37="","",VLOOKUP(B37,'MÃO OBRA'!A$2:F$35064,3,FALSE)) | V37: =IF(B37="","",VLOOKUP(B37,'MÃO OBRA'!A$2:F$21664,6,FALSE)) | X37: =IFERROR(VLOOKUP(B37,'MÃO OBRA'!A:H,8,FALSE),"") | Y37: =IFERROR(VLOOKUP(B37,'MÃO OBRA'!A:I,9,FALSE),"") | Z37: =W37 -> 0 | AA37: =IF(B37="","",(V37*Z37))
A38: =A37+1 -> 12 | C38: =IF(B38="","",VLOOKUP(B38,'MÃO OBRA'!A$2:G$436,2,FALSE)) | U38: =IF(B38="","",VLOOKUP(B38,'MÃO OBRA'!A$2:F$35064,3,FALSE)) | V38: =IF(B38="","",VLOOKUP(B38,'MÃO OBRA'!A$2:F$21664,6,FALSE)) | X38: =IFERROR(VLOOKUP(B38,'MÃO OBRA'!A:H,8,FALSE),"") | Y38: =IFERROR(VLOOKUP(B38,'MÃO OBRA'!A:I,9,FALSE),"") | Z38: =W38 -> 0 | AA38: =IF(B38="","",(V38*Z38))
A39: =A38+1 -> 13 | C39: =IF(B39="","",VLOOKUP(B39,'MÃO OBRA'!A$2:G$436,2,FALSE)) | U39: =IF(B39="","",VLOOKUP(B39,'MÃO OBRA'!A$2:F$35064,3,FALSE)) | V39: =IF(B39="","",VLOOKUP(B39,'MÃO OBRA'!A$2:F$21664,6,FALSE)) | X39: =IFERROR(VLOOKUP(B39,'MÃO OBRA'!A:H,8,FALSE),"") | Y39: =IFERROR(VLOOKUP(B39,'MÃO OBRA'!A:I,9,FALSE),"") | Z39: =W39 -> 0 | AA39: =IF(B39="","",(V39*Z39))
A40: =A39+1 -> 14 | C40: =IF(B40="","",VLOOKUP(B40,'MÃO OBRA'!A$2:G$436,2,FALSE)) | V40: =IF(B40="","",VLOOKUP(B40,'MÃO OBRA'!A$2:F$21664,6,FALSE)) | X40: =IFERROR(VLOOKUP(B40,'MÃO OBRA'!A:H,8,FALSE),"") | Y40: =IFERROR(VLOOKUP(B40,'MÃO OBRA'!A:I,9,FALSE),"") | Z40: =W40 -> 0 | AA40: =IF(B40="","",(V40*Z40))
A41: =A40+1 -> 15 | C41: =IF(B41="","",VLOOKUP(B41,'MÃO OBRA'!A$2:G$436,2,FALSE)) | U41: =IF(B41="","",VLOOKUP(B41,'MÃO OBRA'!A$2:F$35064,3,FALSE)) | V41: =IF(B41="","",VLOOKUP(B41,'MÃO OBRA'!A$2:F$21664,6,FALSE)) | X41: =IFERROR(VLOOKUP(B41,'MÃO OBRA'!A:H,8,FALSE),"") | Y41: =IFERROR(VLOOKUP(B41,'MÃO OBRA'!A:I,9,FALSE),"") | Z41: =W41 -> 0 | AA41: =IF(B41="","",(V41*Z41))
A42: =A41+1 -> 16 | C42: =IF(B42="","",VLOOKUP(B42,'MÃO OBRA'!A$2:G$436,2,FALSE)) | U42: =IF(B42="","",VLOOKUP(B42,'MÃO OBRA'!A$2:F$35064,3,FALSE)) | V42: =IF(B42="","",VLOOKUP(B42,'MÃO OBRA'!A$2:F$21664,6,FALSE)) | X42: =IFERROR(VLOOKUP(B42,'MÃO OBRA'!A:H,8,FALSE),"") | Y42: =IFERROR(VLOOKUP(B42,'MÃO OBRA'!A:I,9,FALSE),"") | Z42: =W42 -> 0 | AA42: =IF(B42="","",(V42*Z42))
A43: =A42+1 -> 17 | C43: =IF(B43="","",VLOOKUP(B43,'MÃO OBRA'!A$2:G$436,2,FALSE)) | U43: =IF(B43="","",VLOOKUP(B43,'MÃO OBRA'!A$2:F$35064,3,FALSE)) | V43: =IF(B43="","",VLOOKUP(B43,'MÃO OBRA'!A$2:F$21664,6,FALSE)) | X43: =IFERROR(VLOOKUP(B43,'MÃO OBRA'!A:H,8,FALSE),"") | Y43: =IFERROR(VLOOKUP(B43,'MÃO OBRA'!A:I,9,FALSE),"") | Z43: =W43 -> 0 | AA43: =IF(B43="","",(V43*Z43))
A44: =A43+1 -> 18 | C44: =IF(B44="","",VLOOKUP(B44,'MÃO OBRA'!A$2:G$436,2,FALSE)) | U44: =IF(B44="","",VLOOKUP(B44,'MÃO OBRA'!A$2:F$35064,3,FALSE)) | V44: =IF(B44="","",VLOOKUP(B44,'MÃO OBRA'!A$2:F$21664,6,FALSE)) | X44: =IFERROR(VLOOKUP(B44,'MÃO OBRA'!A:H,8,FALSE),"") | Y44: =IFERROR(VLOOKUP(B44,'MÃO OBRA'!A:I,9,FALSE),"") | Z44: =W44 -> 0 | AA44: =IF(B44="","",(V44*Z44))
A45: SUB-TOTAL | AA45: =SUM(AA27:AB44) -> 2641.95
A46: 26378 | C46: SERV. EMERG. MOBILIZAÇÃO/DESMOBILIZAÇÃO (1 HORA) | U46: HORA | V46: =IF(W46>0,(243.02),"") | AA46: =V46*W46 -> #VALUE!
A47: 26376 | C47: SERV. EMERG. FORA DO HORARIO COMERCIAL-ADICIONAL 30% | U47: ADIC | V47: =IF(W47>0,(AA45*0.3),"") | AA47: =V47*W47 -> #VALUE!
A48: 26377 | C48: SERV. EMERG. DOMINGO E FERIADO - ADICIONAL 50% | U48: ADIC | V48: =IF(W48>0,(AA45*0.5),"") | AA48: =V48*W48 -> #VALUE!
A49: TOTAL | AA49: =SUM(AA45:AB48) -> #VALUE!
A50: ITEM | B50: CÓD | C50: MATERIAL APLICADO | V50: UN | W50: OPERAÇÕES
Y51: =Y26 -> Ret. | Z51: TOTAL
A52: 1 | B52: 90055 | C52: =IF(B52="","",VLOOKUP(B52,MATERIAL!A:C,2,FALSE)) -> TRANSF DISTR AER OMI 3F 13,8KV 220/127V 75KVA CL2 4TP | V52: =IF(B52="","",VLOOKUP(B52,MATERIAL!A$3:C$531,3,FALSE)) -> #N/A | W52: 1 | Z52: =SUM(W52:Y52) -> 1 | AA52: =IF(B52="","",(V52*Z52)) -> #N/A
A53: 2 | B53: 90210 | C53: =IF(B53="","",VLOOKUP(B53,MATERIAL!A:C,2,FALSE)) -> PARA-RAIOS DISTR MT POLIM 12KV 10KA OX ZN S/CENT S/FERR | V53: =IF(B53="","",VLOOKUP(B53,MATERIAL!A$3:C$531,3,FALSE)) -> UN | W53: 3 | Z53: =SUM(W53:Y53) -> 3 | AA53: =IF(B53="","",(V53*Z53)) -> #VALUE!
A54: 3 | B54: 90207 | C54: =IF(B54="","",VLOOKUP(B54,MATERIAL!A:C,2,FALSE)) -> PARA-RAIOS DISTR BT POLIM 127V 10KA OX MT S/CENT RSI | V54: =IF(B54="","",VLOOKUP(B54,MATERIAL!A$3:C$531,3,FALSE)) -> PC | W54: 3 | Z54: =SUM(W54:Y54) -> 3 | AA54: =IF(B54="","",(V54*Z54)) -> #VALUE!
A55: 4 | B55: 90500 | C55: =IF(B55="","",VLOOKUP(B55,MATERIAL!A:C,2,FALSE)) -> ELO FUSIVEL DISTRIBUICAO TIPO H 3A 500MM | V55: =IF(B55="","",VLOOKUP(B55,MATERIAL!A$3:C$531,3,FALSE)) -> PÇ | W55: 3 | Z55: =SUM(W55:Y55) -> 3 | AA55: =IF(B55="","",(V55*Z55)) -> #VALUE!
A56: 5 | B56: 90342 | C56: =IF(B56="","",VLOOKUP(B56,MATERIAL!A:C,2,FALSE)) -> CONECT TERM ESTRANG CB/BAR ALUM 2F 123X25MM 11.20-12.30MM | V56: UN | W56: 4 | Z56: =SUM(W56:Y56) -> 4 | AA56: =IF(B56="","",(V56*Z56)) -> #VALUE!
A57: 6 | B57: 90294 | C57: =IF(B57="","",VLOOKUP(B57,MATERIAL!A:C,2,FALSE)) -> CABO COBR PROT SPL XLPE 1F 15,0KV 16MM2 BLOQ CNZ | V57: =IF(B57="","",VLOOKUP(B57,MATERIAL!A$3:C$531,3,FALSE)) -> M | W57: 6 | Z57: =SUM(W57:Y57) -> 6 | AA57: =IF(B57="","",(V57*Z57)) -> #VALUE!
A58: 7 | B58: 91462 | C58: =IF(B58="","",VLOOKUP(B58,MATERIAL!A:C,2,FALSE)) -> CABO COBRE ISOLAD 450/750V BWF/PVC 120MM2 CL2/4/5 PRT | V58: =IF(B58="","",VLOOKUP(B58,MATERIAL!A$3:C$531,3,FALSE)) -> M | W58: 6 | Z58: =SUM(W58:Y58) -> 6 | AA58: =IF(B58="","",(V58*Z58)) -> #VALUE!
A59: 8 | B59: 3098 | C59: =IF(B59="","",VLOOKUP(B59,MATERIAL!A:C,2,FALSE)) -> CABO ISOL 750V COBRE PVC/BWF 10MM2 1F CL2 PT | V59: =IF(B59="","",VLOOKUP(B59,MATERIAL!A$3:C$531,3,FALSE)) -> M | W59: 5 | Z59: =SUM(W59:Y59) -> 5 | AA59: =IF(B59="","",(V59*Z59)) -> #VALUE!
A60: 9 | B60: 90355 | C60: =IF(B60="","",VLOOKUP(B60,MATERIAL!A:C,2,FALSE)) -> CONECTOR DERIV PERFURAT C/C 1,0KV 16-120MM2/4-35MM2 | V60: =IF(B60="","",VLOOKUP(B60,MATERIAL!A$3:C$531,3,FALSE)) -> UN | W60: 4 | Z60: =SUM(W60:Y60) -> 4 | AA60: =IF(B60="","",(V60*Z60)) -> #VALUE!
A61: 10 | B61: 90357 | C61: =IF(B61="","",VLOOKUP(B61,MATERIAL!A:C,2,FALSE)) -> CONECTOR DERIV PERFURAT C/C 1,0KV 70-240MM2/70-240MM2 | V61: =IF(B61="","",VLOOKUP(B61,MATERIAL!A$3:C$531,3,FALSE)) -> PC | W61: 4 | Z61: =SUM(W61:Y61) -> 4 | AA61: =IF(B61="","",(V61*Z61)) -> #VALUE!
A62: 11 | B62: 90586 | C62: =IF(B62="","",VLOOKUP(B62,MATERIAL!A:C,2,FALSE)) -> CAPA PROT PEAD TRANSF MT 15/36,2KV 135X110MM | V62: =IF(B62="","",VLOOKUP(B62,MATERIAL!A$3:C$531,3,FALSE)) -> UN | W62: 6 | Z62: =SUM(W62:Y62) -> 6 | AA62: =IF(B62="","",(V62*Z62)) -> #VALUE!
A63: 12 | C63: =IF(B63="","",VLOOKUP(B63,MATERIAL!A:C,2,FALSE)) | V63: =IF(B63="","",VLOOKUP(B63,MATERIAL!A$3:C$531,3,FALSE)) | Z63: =SUM(W63:Y63) -> 0 | AA63: =IF(B63="","",(V63*Z63))
A64: 13 | C64: =IF(B64="","",VLOOKUP(B64,MATERIAL!A:C,2,FALSE)) | V64: =IF(B64="","",VLOOKUP(B64,MATERIAL!A$3:C$531,3,FALSE)) | Z64: =SUM(W64:Y64) -> 0 | AA64: =IF(B64="","",(V64*Z64))
A65: 14 | C65: =IF(B65="","",VLOOKUP(B65,MATERIAL!A:C,2,FALSE)) | V65: =IF(B65="","",VLOOKUP(B65,MATERIAL!A$3:C$531,3,FALSE)) | Z65: =SUM(W65:Y65) -> 0 | AA65: =IF(B65="","",(V65*Z65))
A66: 15 | C66: =IF(B66="","",VLOOKUP(B66,MATERIAL!A:C,2,FALSE)) | V66: =IF(B66="","",VLOOKUP(B66,MATERIAL!A$3:C$531,3,FALSE)) | Z66: =SUM(W66:Y66) -> 0 | AA66: =IF(B66="","",(V66*Z66))
A67: 16 | C67: =IF(B67="","",VLOOKUP(B67,MATERIAL!A:C,2,FALSE)) | V67: =IF(B67="","",VLOOKUP(B67,MATERIAL!A$3:C$531,3,FALSE)) | Z67: =SUM(W67:Y67) -> 0 | AA67: =IF(B67="","",(V67*Z67))
A68: 17 | C68: =IF(B68="","",VLOOKUP(B68,MATERIAL!A:C,2,FALSE)) | V68: =IF(B68="","",VLOOKUP(B68,MATERIAL!A$3:C$531,3,FALSE)) | Z68: =SUM(W68:Y68) -> 0 | AA68: =IF(B68="","",(V68*Z68))
A69: 18 | C69: =IF(B69="","",VLOOKUP(B69,MATERIAL!A:C,2,FALSE)) | V69: =IF(B69="","",VLOOKUP(B69,MATERIAL!A$3:C$531,3,FALSE)) | Z69: =SUM(W69:Y69) -> 0 | AA69: =IF(B69="","",(V69*Z69))
A70: 19 | C70: =IF(B70="","",VLOOKUP(B70,MATERIAL!A:C,2,FALSE)) | V70: =IF(B70="","",VLOOKUP(B70,MATERIAL!A$3:C$531,3,FALSE)) | Z70: =SUM(W70:Y70) -> 0
A71: 20 | C71: =IF(B71="","",VLOOKUP(B71,MATERIAL!A:C,2,FALSE)) | V71: =IF(B71="","",VLOOKUP(B71,MATERIAL!A$3:C$531,3,FALSE)) | Z71: =SUM(W71:Y71) -> 0
A72: 21 | C72: =IF(B72="","",VLOOKUP(B72,MATERIAL!A:C,2,FALSE)) | V72: =IF(B72="","",VLOOKUP(B72,MATERIAL!A$3:C$531,3,FALSE)) | Z72: =SUM(W72:Y72) -> 0
A73: 22 | C73: =IF(B73="","",VLOOKUP(B73,MATERIAL!A:C,2,FALSE)) | V73: =IF(B73="","",VLOOKUP(B73,MATERIAL!A$3:C$531,3,FALSE)) | Z73: =SUM(W73:Y73) -> 0
A74: ITEM | B74: CÓD | C74: MATERIAL RETIRADO | V74: UN | W74: OPERAÇÕES | AB74: TOTAL
W75: SUCATA | X75: REFORMA | Z75: BOM | AA75: DESCARTE
A76: 1 | B76: 90054 | C76: =IF(B76="","",VLOOKUP(B76,MATERIAL!A:C,2,FALSE)) -> TRANSF DISTR AER OMI 3F 13,8KV 220/127V 45KVA CL2 4TP | V76: =IF(B76="","",VLOOKUP(B76,MATERIAL!A$3:C$531,3,FALSE)) -> #N/A | X76: 1 | AB76: =SUM(W76:AA76) -> 1
A77: 2 | B77: 90210 | C77: =IF(B77="","",VLOOKUP(B77,MATERIAL!A:C,2,FALSE)) -> PARA-RAIOS DISTR MT POLIM 12KV 10KA OX ZN S/CENT S/FERR | V77: =IF(B77="","",VLOOKUP(B77,MATERIAL!A$3:C$531,3,FALSE)) -> UN | W77: 3 | AB77: =SUM(W77:AA77) -> 3
A78: 3 | B78: 90500 | C78: =IF(B78="","",VLOOKUP(B78,MATERIAL!A:C,2,FALSE)) -> ELO FUSIVEL DISTRIBUICAO TIPO H 3A 500MM | V78: =IF(B78="","",VLOOKUP(B78,MATERIAL!A$3:C$531,3,FALSE)) -> PÇ | W78: 3 | AB78: =SUM(W78:AA78) -> 3
A79: 4 | B79: 90586 | C79: =IF(B79="","",VLOOKUP(B79,MATERIAL!A:C,2,FALSE)) -> CAPA PROT PEAD TRANSF MT 15/36,2KV 135X110MM | V79: =IF(B79="","",VLOOKUP(B79,MATERIAL!A$3:C$531,3,FALSE)) -> UN | W79: 6 | AB79: =SUM(W79:AA79) -> 6
A80: 5 | C80: =IF(B80="","",VLOOKUP(B80,MATERIAL!A:C,2,FALSE)) | V80: =IF(B80="","",VLOOKUP(B80,MATERIAL!A$3:C$531,3,FALSE)) | AB80: =SUM(W80:AA80) -> 0
A81: 6 | C81: =IF(B81="","",VLOOKUP(B81,MATERIAL!A:C,2,FALSE)) | V81: =IF(B81="","",VLOOKUP(B81,MATERIAL!A$3:C$531,3,FALSE)) | AB81: =SUM(W81:AA81) -> 0
A82: 7 | C82: =IF(B82="","",VLOOKUP(B82,MATERIAL!A:C,2,FALSE)) | V82: =IF(B82="","",VLOOKUP(B82,MATERIAL!A$3:C$531,3,FALSE)) | AB82: =SUM(W82:AA82) -> 0
A83: 8 | C83: =IF(B83="","",VLOOKUP(B83,MATERIAL!A:C,2,FALSE)) | V83: =IF(B83="","",VLOOKUP(B83,MATERIAL!A$3:C$531,3,FALSE)) | AB83: =SUM(W83:AA83) -> 0
A84: 9 | C84: =IF(B84="","",VLOOKUP(B84,MATERIAL!A:C,2,FALSE)) | V84: =IF(B84="","",VLOOKUP(B84,MATERIAL!A$3:C$531,3,FALSE)) | AB84: =SUM(W84:AA84) -> 0
A85: 10 | C85: =IF(B85="","",VLOOKUP(B85,MATERIAL!A:C,2,FALSE)) | V85: =IF(B85="","",VLOOKUP(B85,MATERIAL!A$3:C$531,3,FALSE)) | AB85: =SUM(W85:AA85) -> 0
A86: 11 | C86: =IF(B86="","",VLOOKUP(B86,MATERIAL!A:C,2,FALSE)) | V86: =IF(B86="","",VLOOKUP(B86,MATERIAL!A$3:C$531,3,FALSE)) | AB86: =SUM(W86:AA86) -> 0
A87: 12 | C87: =IF(B87="","",VLOOKUP(B87,MATERIAL!A:C,2,FALSE)) | V87: =IF(B87="","",VLOOKUP(B87,MATERIAL!A$3:C$531,3,FALSE)) | AB87: =SUM(W87:AA87) -> 0

Sheet 5702814005 4575
A2: EQUIPE=> | B2: 147 | C2: ENCARREGADO: | G2: FERNANDO | I2: DATA SAÍDA=> | L2: Terça-feira, 3 de maio de 2022 | R2: DATA RETORNO=> | S2: Terça-feira, 3 de maio de 2022 | W2: TÉCNICO DIN: | Z2: ARINEY
A4: ENDEREÇO=> | C4: Av. Flamboiant, 2-118 - Res. Sao Carlos, Cuiabá - MT, 78051-035 | V4: NR | X4: DINEM20220***
A6: ELETRICISTAS=> | C6: GESSER / LUCICLAUDIO
A8: SAIDA BASE => | C8: 08:35 | G8: RETORNO BASE => | K8: 0.73958333 | O8: =K8-C8 -> 0.38194444 | R8: KM INICIAL=> | T8: 59600 | V8: =T10-T8 -> 30 | AB8: KM
A10: INICIO SERVIÇO => | C10: 10:45 | G10: RETORNO SERVIÇO => | K10: 0.50069444 | O10: =K10-C10 -> 0.052777778 | R10: KM FINAL=> | T10: 59630
A12: CÓD. ACIONAMENTO=> | G12: Nº INTERVENÇÃO=> | J12: 20222986520197 | Q12: NOTA (SS)=> | S12: EMT-RD-ME002901/2022 | W12: OS TABLET =>
A14: OBSERVAÇÃO =>
A16: TRANSFORMADOR RETIRADO POTENCIA => | G16: 45 KVA | I16: MARCA => | L16: WEG | P16: FABRICAÇÃO => | R16: 07 / 1992
A17: TENSÃO SEGUNDARIA=> | C17: 127/220 | F17: V | G17: TENSÃO PRIMARIA=> | J17: 44786 | M17: KV | O17: Nº SERIE => | R17: 81439 | V17: PATRIMONIO => | Y17: 10004
A19: TRANSFORMADOR INSTALADO POTENCIA => | G19: 75 KVA | I19: MARCA => | L19: ITAIPU | P19: FABRICAÇÃO => | R19: 06 / 2021
A20: TENSÃO SEGUNDARIA=> | C20: 127/220 | F20: V | G20: TENSÃO PRIMARIA=> | J20: 44786 | M20: KV | O20: Nº SERIE => | R20: 435805 | V20: PATRIMONIO => | Y20: 270154
A21: A-N=> | B21: 120 | C21: B-N=> | E21: 122 | G21: C-N=> | H21: 126 | I21: A-B=> | K21: 225 | L21: A-C=> | M21: 215 | O21: B-C=> | Q21: 218 | S21: A=> | T21: 38 | U21: B=> | V21: 20 | W21: C=> | X21: 38 | Z21: N=> | AA21: 16
A23: ALIMENTADOR => | G23: SUBESTAÇÃO => | L23: Nº TRANSFORMADOR => | Q23: 5702814005 | T23: Nº ID POSTE =>
A25: ITEM | B25: CÓD | U25: Un | V25: R$ | W25: OPERAÇÕES
X26: Inst. | Y26: Ret. | Z26: TOTAL | AA26: R$
A27: 1 | B27: 6061 | C27: =IF(B27="","",VLOOKUP(B27,'MÃO OBRA'!A$2:G$436,2,FALSE)) -> DESAT TRANSF DISTRIBUIC AEREO 3F LM | U27: =IF(B27="","",VLOOKUP(B27,'MÃO OBRA'!A$2:F$35064,3,FALSE)) -> 0 | V27: =IF(B27="","",VLOOKUP(B27,'MÃO OBRA'!A$2:F$21664,6,FALSE)) -> 287.17 | W27: 1 | X27: =IFERROR(VLOOKUP(B27,'MÃO OBRA'!A:H,8,FALSE),"") -> 0 | Y27: =IFERROR(VLOOKUP(B27,'MÃO OBRA'!A:I,9,FALSE),"") -> 0 | Z27: =W27 -> 1 | AA27: =IF(B27="","",(V27*Z27)) -> 287.17
A28: =A27+1 -> 2 | B28: 6093 | C28: =IF(B28="","",VLOOKUP(B28,'MÃO OBRA'!A$2:G$436,2,FALSE)) -> INST TRANSF DISTRIBUIC AEREO TRIF LM | U28: =IF(B28="","",VLOOKUP(B28,'MÃO OBRA'!A$2:F$35064,3,FALSE)) -> UN | V28: =IF(B28="","",VLOOKUP(B28,'MÃO OBRA'!A$2:F$21664,6,FALSE)) -> 1052.94 | W28: 1 | X28: =IFERROR(VLOOKUP(B28,'MÃO OBRA'!A:H,8,FALSE),"") -> x | Y28: =IFERROR(VLOOKUP(B28,'MÃO OBRA'!A:I,9,FALSE),"") -> 0 | Z28: =W28 -> 1 | AA28: =IF(B28="","",(V28*Z28)) -> 1052.94
A29: =A28+1 -> 3 | B29: 7038 | C29: =IF(B29="","",VLOOKUP(B29,'MÃO OBRA'!A$2:G$436,2,FALSE)) -> #N/A | U29: =IF(B29="","",VLOOKUP(B29,'MÃO OBRA'!A$2:F$35064,3,FALSE)) -> UN | V29: =IF(B29="","",VLOOKUP(B29,'MÃO OBRA'!A$2:F$21664,6,FALSE)) -> 124.44 | W29: 1 | X29: =IFERROR(VLOOKUP(B29,'MÃO OBRA'!A:H,8,FALSE),"") -> 0 | Y29: =IFERROR(VLOOKUP(B29,'MÃO OBRA'!A:I,9,FALSE),"") -> x | Z29: =W29 -> 1 | AA29: =IF(B29="","",(V29*Z29)) -> 124.44
A30: =A29+1 -> 4 | B30: 6171 | C30: =IF(B30="","",VLOOKUP(B30,'MÃO OBRA'!A$2:G$436,2,FALSE)) -> OPER CHAVE FUS AB E FC EMERG LM | U30: =IF(B30="","",VLOOKUP(B30,'MÃO OBRA'!A$2:F$35064,3,FALSE)) -> UN | V30: =IF(B30="","",VLOOKUP(B30,'MÃO OBRA'!A$2:F$21664,6,FALSE)) -> 47.86 | W30: 3 | X30: =IFERROR(VLOOKUP(B30,'MÃO OBRA'!A:H,8,FALSE),"") -> x | Y30: =IFERROR(VLOOKUP(B30,'MÃO OBRA'!A:I,9,FALSE),"") -> 0 | Z30: =W30 -> 3 | AA30: =IF(B30="","",(V30*Z30)) -> 143.58
A31: =A30+1 -> 5 | B31: 6501 | C31: =IF(B31="","",VLOOKUP(B31,'MÃO OBRA'!A$2:G$436,2,FALSE)) -> SUBST ELO FUSIVEL LM | U31: =IF(B31="","",VLOOKUP(B31,'MÃO OBRA'!A$2:F$35064,3,FALSE)) -> 0 | V31: =IF(B31="","",VLOOKUP(B31,'MÃO OBRA'!A$2:F$21664,6,FALSE)) -> 47.86 | W31: 3 | X31: =IFERROR(VLOOKUP(B31,'MÃO OBRA'!A:H,8,FALSE),"") -> 0 | Y31: =IFERROR(VLOOKUP(B31,'MÃO OBRA'!A:I,9,FALSE),"") -> 0 | Z31: =W31 -> 3 | AA31: =IF(B31="","",(V31*Z31)) -> 143.58
A32: 6 | B32: 6082 | C32: =IF(B32="","",VLOOKUP(B32,'MÃO OBRA'!A$2:G$436,2,FALSE)) -> INST PARA-RAIOS RD < 34,5 KV LM | U32: =IF(B32="","",VLOOKUP(B32,'MÃO OBRA'!A$2:F$35064,3,FALSE)) -> UN | V32: =IF(B32="","",VLOOKUP(B32,'MÃO OBRA'!A$2:F$21664,6,FALSE)) -> 95.72 | W32: 3 | X32: =IFERROR(VLOOKUP(B32,'MÃO OBRA'!A:H,8,FALSE),"") -> x | Y32: =IFERROR(VLOOKUP(B32,'MÃO OBRA'!A:I,9,FALSE),"") -> 0 | Z32: =W32 -> 3 | AA32: =IF(B32="","",(V32*Z32)) -> 287.16
A33: =A32+1 -> 7 | B33: 6083 | C33: =IF(B33="","",VLOOKUP(B33,'MÃO OBRA'!A$2:G$436,2,FALSE)) -> INST PARA-RAIOS RD => 34,5 KV LM | U33: =IF(B33="","",VLOOKUP(B33,'MÃO OBRA'!A$2:F$35064,3,FALSE)) -> UN | V33: =IF(B33="","",VLOOKUP(B33,'MÃO OBRA'!A$2:F$21664,6,FALSE)) -> 95.72 | W33: 3 | X33: =IFERROR(VLOOKUP(B33,'MÃO OBRA'!A:H,8,FALSE),"") -> x | Y33: =IFERROR(VLOOKUP(B33,'MÃO OBRA'!A:I,9,FALSE),"") -> 0 | Z33: =W33 -> 3 | AA33: =IF(B33="","",(V33*Z33)) -> 287.16
A34: =A33+1 -> 8 | B34: 6235 | C34: =IF(B34="","",VLOOKUP(B34,'MÃO OBRA'!A$2:G$436,2,FALSE)) -> INST CONEC RD SEC LM | U34: =IF(B34="","",VLOOKUP(B34,'MÃO OBRA'!A$2:F$35064,3,FALSE)) -> UN | V34: =IF(B34="","",VLOOKUP(B34,'MÃO OBRA'!A$2:F$21664,6,FALSE)) -> 9.58 | W34: 8 | X34: =IFERROR(VLOOKUP(B34,'MÃO OBRA'!A:H,8,FALSE),"") -> x | Y34: =IFERROR(VLOOKUP(B34,'MÃO OBRA'!A:I,9,FALSE),"") -> 0 | Z34: =W34 -> 8 | AA34: =IF(B34="","",(V34*Z34)) -> 76.64
A35: =A34+1 -> 9 | B35: 6055 | C35: =IF(B35="","",VLOOKUP(B35,'MÃO OBRA'!A$2:G$436,2,FALSE)) -> DESAT PARA-RAIOS RD < 34,5 KV LM | U35: =IF(B35="","",VLOOKUP(B35,'MÃO OBRA'!A$2:F$35064,3,FALSE)) -> 0 | V35: =IF(B35="","",VLOOKUP(B35,'MÃO OBRA'!A$2:F$21664,6,FALSE)) -> 28.72 | W35: 3 | X35: =IFERROR(VLOOKUP(B35,'MÃO OBRA'!A:H,8,FALSE),"") -> 0 | Y35: =IFERROR(VLOOKUP(B35,'MÃO OBRA'!A:I,9,FALSE),"") -> 0 | Z35: =W35 -> 3 | AA35: =IF(B35="","",(V35*Z35)) -> 86.16
A36: =A35+1 -> 10 | B36: 7640 | C36: =IF(B36="","",VLOOKUP(B36,'MÃO OBRA'!A$2:G$436,2,FALSE)) -> #N/A | U36: =IF(B36="","",VLOOKUP(B36,'MÃO OBRA'!A$2:F$35064,3,FALSE)) -> 0 | V36: =IF(B36="","",VLOOKUP(B36,'MÃO OBRA'!A$2:F$21664,6,FALSE)) -> 19.14 | W36: 8 | X36: =IFERROR(VLOOKUP(B36,'MÃO OBRA'!A:H,8,FALSE),"") -> 0 | Y36: =IFERROR(VLOOKUP(B36,'MÃO OBRA'!A:I,9,FALSE),"") -> 0 | Z36: =W36 -> 8 | AA36: =IF(B36="","",(V36*Z36)) -> 153.12
A37: =A36+1 -> 11 | C37: =IF(B37="","",VLOOKUP(B37,'MÃO OBRA'!A$2:G$436,2,FALSE)) | U37: =IF(B37="","",VLOOKUP(B37,'MÃO OBRA'!A$2:F$35064,3,FALSE)) | V37: =IF(B37="","",VLOOKUP(B37,'MÃO OBRA'!A$2:F$21664,6,FALSE)) | X37: =IFERROR(VLOOKUP(B37,'MÃO OBRA'!A:H,8,FALSE),"") | Y37: =IFERROR(VLOOKUP(B37,'MÃO OBRA'!A:I,9,FALSE),"") | Z37: =W37 -> 0 | AA37: =IF(B37="","",(V37*Z37))
A38: =A37+1 -> 12 | C38: =IF(B38="","",VLOOKUP(B38,'MÃO OBRA'!A$2:G$436,2,FALSE)) | U38: =IF(B38="","",VLOOKUP(B38,'MÃO OBRA'!A$2:F$35064,3,FALSE)) | V38: =IF(B38="","",VLOOKUP(B38,'MÃO OBRA'!A$2:F$21664,6,FALSE)) | X38: =IFERROR(VLOOKUP(B38,'MÃO OBRA'!A:H,8,FALSE),"") | Y38: =IFERROR(VLOOKUP(B38,'MÃO OBRA'!A:I,9,FALSE),"") | Z38: =W38 -> 0 | AA38: =IF(B38="","",(V38*Z38))
A39: =A38+1 -> 13 | C39: =IF(B39="","",VLOOKUP(B39,'MÃO OBRA'!A$2:G$436,2,FALSE)) | U39: =IF(B39="","",VLOOKUP(B39,'MÃO OBRA'!A$2:F$35064,3,FALSE)) | V39: =IF(B39="","",VLOOKUP(B39,'MÃO OBRA'!A$2:F$21664,6,FALSE)) | X39: =IFERROR(VLOOKUP(B39,'MÃO OBRA'!A:H,8,FALSE),"") | Y39: =IFERROR(VLOOKUP(B39,'MÃO OBRA'!A:I,9,FALSE),"") | Z39: =W39 -> 0 | AA39: =IF(B39="","",(V39*Z39))
A40: =A39+1 -> 14 | C40: =IF(B40="","",VLOOKUP(B40,'MÃO OBRA'!A$2:G$436,2,FALSE)) | V40: =IF(B40="","",VLOOKUP(B40,'MÃO OBRA'!A$2:F$21664,6,FALSE)) | X40: =IFERROR(VLOOKUP(B40,'MÃO OBRA'!A:H,8,FALSE),"") | Y40: =IFERROR(VLOOKUP(B40,'MÃO OBRA'!A:I,9,FALSE),"") | Z40: =W40 -> 0 | AA40: =IF(B40="","",(V40*Z40))
A41: =A40+1 -> 15 | C41: =IF(B41="","",VLOOKUP(B41,'MÃO OBRA'!A$2:G$436,2,FALSE)) | U41: =IF(B41="","",VLOOKUP(B41,'MÃO OBRA'!A$2:F$35064,3,FALSE)) | V41: =IF(B41="","",VLOOKUP(B41,'MÃO OBRA'!A$2:F$21664,6,FALSE)) | X41: =IFERROR(VLOOKUP(B41,'MÃO OBRA'!A:H,8,FALSE),"") | Y41: =IFERROR(VLOOKUP(B41,'MÃO OBRA'!A:I,9,FALSE),"") | Z41: =W41 -> 0 | AA41: =IF(B41="","",(V41*Z41))
A42: =A41+1 -> 16 | C42: =IF(B42="","",VLOOKUP(B42,'MÃO OBRA'!A$2:G$436,2,FALSE)) | U42: =IF(B42="","",VLOOKUP(B42,'MÃO OBRA'!A$2:F$35064,3,FALSE)) | V42: =IF(B42="","",VLOOKUP(B42,'MÃO OBRA'!A$2:F$21664,6,FALSE)) | X42: =IFERROR(VLOOKUP(B42,'MÃO OBRA'!A:H,8,FALSE),"") | Y42: =IFERROR(VLOOKUP(B42,'MÃO OBRA'!A:I,9,FALSE),"") | Z42: =W42 -> 0 | AA42: =IF(B42="","",(V42*Z42))
A43: =A42+1 -> 17 | C43: =IF(B43="","",VLOOKUP(B43,'MÃO OBRA'!A$2:G$436,2,FALSE)) | U43: =IF(B43="","",VLOOKUP(B43,'MÃO OBRA'!A$2:F$35064,3,FALSE)) | V43: =IF(B43="","",VLOOKUP(B43,'MÃO OBRA'!A$2:F$21664,6,FALSE)) | X43: =IFERROR(VLOOKUP(B43,'MÃO OBRA'!A:H,8,FALSE),"") | Y43: =IFERROR(VLOOKUP(B43,'MÃO OBRA'!A:I,9,FALSE),"") | Z43: =W43 -> 0 | AA43: =IF(B43="","",(V43*Z43))
A44: =A43+1 -> 18 | C44: =IF(B44="","",VLOOKUP(B44,'MÃO OBRA'!A$2:G$436,2,FALSE)) | U44: =IF(B44="","",VLOOKUP(B44,'MÃO OBRA'!A$2:F$35064,3,FALSE)) | V44: =IF(B44="","",VLOOKUP(B44,'MÃO OBRA'!A$2:F$21664,6,FALSE)) | X44: =IFERROR(VLOOKUP(B44,'MÃO OBRA'!A:H,8,FALSE),"") | Y44: =IFERROR(VLOOKUP(B44,'MÃO OBRA'!A:I,9,FALSE),"") | Z44: =W44 -> 0 | AA44: =IF(B44="","",(V44*Z44))
A45: SUB-TOTAL | AA45: =SUM(AA27:AB44) -> 2641.95
A46: 26378 | C46: SERV. EMERG. MOBILIZAÇÃO/DESMOBILIZAÇÃO (1 HORA) | U46: HORA | V46: =IF(W46>0,(243.02),"") | AA46: =V46*W46 -> #VALUE!
A47: 26376 | C47: SERV. EMERG. FORA DO HORARIO COMERCIAL-ADICIONAL 30% | U47: ADIC | V47: =IF(W47>0,(AA45*0.3),"") | AA47: =V47*W47 -> #VALUE!
A48: 26377 | C48: SERV. EMERG. DOMINGO E FERIADO - ADICIONAL 50% | U48: ADIC | V48: =IF(W48>0,(AA45*0.5),"") | AA48: =V48*W48 -> #VALUE!
A49: TOTAL | AA49: =SUM(AA45:AB48) -> #VALUE!
A50: ITEM | B50: CÓD | C50: MATERIAL APLICADO | V50: UN | W50: OPERAÇÕES
Y51: =Y26 -> Ret. | Z51: TOTAL
A52: 1 | B52: 90055 | C52: =IF(B52="","",VLOOKUP(B52,MATERIAL!A:C,2,FALSE)) -> TRANSF DISTR AER OMI 3F 13,8KV 220/127V 75KVA CL2 4TP | V52: =IF(B52="","",VLOOKUP(B52,MATERIAL!A$3:C$531,3,FALSE)) -> #N/A | W52: 1 | Z52: =SUM(W52:Y52) -> 1 | AA52: =IF(B52="","",(V52*Z52)) -> #N/A
A53: 2 | B53: 90210 | C53: =IF(B53="","",VLOOKUP(B53,MATERIAL!A:C,2,FALSE)) -> PARA-RAIOS DISTR MT POLIM 12KV 10KA OX ZN S/CENT S/FERR | V53: =IF(B53="","",VLOOKUP(B53,MATERIAL!A$3:C$531,3,FALSE)) -> UN | W53: 3 | Z53: =SUM(W53:Y53) -> 3 | AA53: =IF(B53="","",(V53*Z53)) -> #VALUE!
A54: 3 | B54: 90207 | C54: =IF(B54="","",VLOOKUP(B54,MATERIAL!A:C,2,FALSE)) -> PARA-RAIOS DISTR BT POLIM 127V 10KA OX MT S/CENT RSI | V54: =IF(B54="","",VLOOKUP(B54,MATERIAL!A$3:C$531,3,FALSE)) -> PC | W54: 3 | Z54: =SUM(W54:Y54) -> 3 | AA54: =IF(B54="","",(V54*Z54)) -> #VALUE!
A55: 4 | B55: 90500 | C55: =IF(B55="","",VLOOKUP(B55,MATERIAL!A:C,2,FALSE)) -> ELO FUSIVEL DISTRIBUICAO TIPO H 3A 500MM | V55: =IF(B55="","",VLOOKUP(B55,MATERIAL!A$3:C$531,3,FALSE)) -> PÇ | W55: 3 | Z55: =SUM(W55:Y55) -> 3 | AA55: =IF(B55="","",(V55*Z55)) -> #VALUE!
A56: 5 | B56: 90342 | C56: =IF(B56="","",VLOOKUP(B56,MATERIAL!A:C,2,FALSE)) -> CONECT TERM ESTRANG CB/BAR ALUM 2F 123X25MM 11.20-12.30MM | V56: UN | W56: 4 | Z56: =SUM(W56:Y56) -> 4 | AA56: =IF(B56="","",(V56*Z56)) -> #VALUE!
A57: 6 | B57: 90294 | C57: =IF(B57="","",VLOOKUP(B57,MATERIAL!A:C,2,FALSE)) -> CABO COBR PROT SPL XLPE 1F 15,0KV 16MM2 BLOQ CNZ | V57: =IF(B57="","",VLOOKUP(B57,MATERIAL!A$3:C$531,3,FALSE)) -> M | W57: 6 | Z57: =SUM(W57:Y57) -> 6 | AA57: =IF(B57="","",(V57*Z57)) -> #VALUE!
A58: 7 | B58: 91462 | C58: =IF(B58="","",VLOOKUP(B58,MATERIAL!A:C,2,FALSE)) -> CABO COBRE ISOLAD 450/750V BWF/PVC 120MM2 CL2/4/5 PRT | V58: =IF(B58="","",VLOOKUP(B58,MATERIAL!A$3:C$531,3,FALSE)) -> M | W58: 6 | Z58: =SUM(W58:Y58) -> 6 | AA58: =IF(B58="","",(V58*Z58)) -> #VALUE!
A59: 8 | B59: 3098 | C59: =IF(B59="","",VLOOKUP(B59,MATERIAL!A:C,2,FALSE)) -> CABO ISOL 750V COBRE PVC/BWF 10MM2 1F CL2 PT | V59: =IF(B59="","",VLOOKUP(B59,MATERIAL!A$3:C$531,3,FALSE)) -> M | W59: 5 | Z59: =SUM(W59:Y59) -> 5 | AA59: =IF(B59="","",(V59*Z59)) -> #VALUE!
A60: 9 | B60: 90355 | C60: =IF(B60="","",VLOOKUP(B60,MATERIAL!A:C,2,FALSE)) -> CONECTOR DERIV PERFURAT C/C 1,0KV 16-120MM2/4-35MM2 | V60: =IF(B60="","",VLOOKUP(B60,MATERIAL!A$3:C$531,3,FALSE)) -> UN | W60: 4 | Z60: =SUM(W60:Y60) -> 4 | AA60: =IF(B60="","",(V60*Z60)) -> #VALUE!
A61: 10 | B61: 90357 | C61: =IF(B61="","",VLOOKUP(B61,MATERIAL!A:C,2,FALSE)) -> CONECTOR DERIV PERFURAT C/C 1,0KV 70-240MM2/70-240MM2 | V61: =IF(B61="","",VLOOKUP(B61,MATERIAL!A$3:C$531,3,FALSE)) -> PC | W61: 4 | Z61: =SUM(W61:Y61) -> 4 | AA61: =IF(B61="","",(V61*Z61)) -> #VALUE!
A62: 11 | B62: 90586 | C62: =IF(B62="","",VLOOKUP(B62,MATERIAL!A:C,2,FALSE)) -> CAPA PROT PEAD TRANSF MT 15/36,2KV 135X110MM | V62: =IF(B62="","",VLOOKUP(B62,MATERIAL!A$3:C$531,3,FALSE)) -> UN | W62: 6 | Z62: =SUM(W62:Y62) -> 6 | AA62: =IF(B62="","",(V62*Z62)) -> #VALUE!
A63: 12 | C63: =IF(B63="","",VLOOKUP(B63,MATERIAL!A:C,2,FALSE)) | V63: =IF(B63="","",VLOOKUP(B63,MATERIAL!A$3:C$531,3,FALSE)) | Z63: =SUM(W63:Y63) -> 0 | AA63: =IF(B63="","",(V63*Z63))
A64: 13 | C64: =IF(B64="","",VLOOKUP(B64,MATERIAL!A:C,2,FALSE)) | V64: =IF(B64="","",VLOOKUP(B64,MATERIAL!A$3:C$531,3,FALSE)) | Z64: =SUM(W64:Y64) -> 0 | AA64: =IF(B64="","",(V64*Z64))
A65: 14 | C65: =IF(B65="","",VLOOKUP(B65,MATERIAL!A:C,2,FALSE)) | V65: =IF(B65="","",VLOOKUP(B65,MATERIAL!A$3:C$531,3,FALSE)) | Z65: =SUM(W65:Y65) -> 0 | AA65: =IF(B65="","",(V65*Z65))
A66: 15 | C66: =IF(B66="","",VLOOKUP(B66,MATERIAL!A:C,2,FALSE)) | V66: =IF(B66="","",VLOOKUP(B66,MATERIAL!A$3:C$531,3,FALSE)) | Z66: =SUM(W66:Y66) -> 0 | AA66: =IF(B66="","",(V66*Z66))
A67: 16 | C67: =IF(B67="","",VLOOKUP(B67,MATERIAL!A:C,2,FALSE)) | V67: =IF(B67="","",VLOOKUP(B67,MATERIAL!A$3:C$531,3,FALSE)) | Z67: =SUM(W67:Y67) -> 0 | AA67: =IF(B67="","",(V67*Z67))
A68: 17 | C68: =IF(B68="","",VLOOKUP(B68,MATERIAL!A:C,2,FALSE)) | V68: =IF(B68="","",VLOOKUP(B68,MATERIAL!A$3:C$531,3,FALSE)) | Z68: =SUM(W68:Y68) -> 0 | AA68: =IF(B68="","",(V68*Z68))
A69: 18 | C69: =IF(B69="","",VLOOKUP(B69,MATERIAL!A:C,2,FALSE)) | V69: =IF(B69="","",VLOOKUP(B69,MATERIAL!A$3:C$531,3,FALSE)) | Z69: =SUM(W69:Y69) -> 0 | AA69: =IF(B69="","",(V69*Z69))
A70: 19 | C70: =IF(B70="","",VLOOKUP(B70,MATERIAL!A:C,2,FALSE)) | V70: =IF(B70="","",VLOOKUP(B70,MATERIAL!A$3:C$531,3,FALSE)) | Z70: =SUM(W70:Y70) -> 0
A71: 20 | C71: =IF(B71="","",VLOOKUP(B71,MATERIAL!A:C,2,FALSE)) | V71: =IF(B71="","",VLOOKUP(B71,MATERIAL!A$3:C$531,3,FALSE)) | Z71: =SUM(W71:Y71) -> 0
A72: 21 | C72: =IF(B72="","",VLOOKUP(B72,MATERIAL!A:C,2,FALSE)) | V72: =IF(B72="","",VLOOKUP(B72,MATERIAL!A$3:C$531,3,FALSE)) | Z72: =SUM(W72:Y72) -> 0
A73: 22 | C73: =IF(B73="","",VLOOKUP(B73,MATERIAL!A:C,2,FALSE)) | V73: =IF(B73="","",VLOOKUP(B73,MATERIAL!A$3:C$531,3,FALSE)) | Z73: =SUM(W73:Y73) -> 0
A74: ITEM | B74: CÓD | C74: MATERIAL RETIRADO | V74: UN | W74: OPERAÇÕES | AB74: TOTAL
W75: SUCATA | X75: REFORMA | Z75: BOM | AA75: DESCARTE
A76: 1 | B76: 90054 | C76: =IF(B76="","",VLOOKUP(B76,MATERIAL!A:C,2,FALSE)) -> TRANSF DISTR AER OMI 3F 13,8KV 220/127V 45KVA CL2 4TP | V76: =IF(B76="","",VLOOKUP(B76,MATERIAL!A$3:C$531,3,FALSE)) -> #N/A | X76: 1 | AB76: =SUM(W76:AA76) -> 1
A77: 2 | B77: 90210 | C77: =IF(B77="","",VLOOKUP(B77,MATERIAL!A:C,2,FALSE)) -> PARA-RAIOS DISTR MT POLIM 12KV 10KA OX ZN S/CENT S/FERR | V77: =IF(B77="","",VLOOKUP(B77,MATERIAL!A$3:C$531,3,FALSE)) -> UN | W77: 3 | AB77: =SUM(W77:AA77) -> 3
A78: 3 | B78: 90500 | C78: =IF(B78="","",VLOOKUP(B78,MATERIAL!A:C,2,FALSE)) -> ELO FUSIVEL DISTRIBUICAO TIPO H 3A 500MM | V78: =IF(B78="","",VLOOKUP(B78,MATERIAL!A$3:C$531,3,FALSE)) -> PÇ | W78: 3 | AB78: =SUM(W78:AA78) -> 3
A79: 4 | B79: 90586 | C79: =IF(B79="","",VLOOKUP(B79,MATERIAL!A:C,2,FALSE)) -> CAPA PROT PEAD TRANSF MT 15/36,2KV 135X110MM | V79: =IF(B79="","",VLOOKUP(B79,MATERIAL!A$3:C$531,3,FALSE)) -> UN | W79: 6 | AB79: =SUM(W79:AA79) -> 6
A80: 5 | C80: =IF(B80="","",VLOOKUP(B80,MATERIAL!A:C,2,FALSE)) | V80: =IF(B80="","",VLOOKUP(B80,MATERIAL!A$3:C$531,3,FALSE)) | AB80: =SUM(W80:AA80) -> 0
A81: 6 | C81: =IF(B81="","",VLOOKUP(B81,MATERIAL!A:C,2,FALSE)) | V81: =IF(B81="","",VLOOKUP(B81,MATERIAL!A$3:C$531,3,FALSE)) | AB81: =SUM(W81:AA81) -> 0
A82: 7 | C82: =IF(B82="","",VLOOKUP(B82,MATERIAL!A:C,2,FALSE)) | V82: =IF(B82="","",VLOOKUP(B82,MATERIAL!A$3:C$531,3,FALSE)) | AB82: =SUM(W82:AA82) -> 0
A83: 8 | C83: =IF(B83="","",VLOOKUP(B83,MATERIAL!A:C,2,FALSE)) | V83: =IF(B83="","",VLOOKUP(B83,MATERIAL!A$3:C$531,3,FALSE)) | AB83: =SUM(W83:AA83) -> 0
A84: 9 | C84: =IF(B84="","",VLOOKUP(B84,MATERIAL!A:C,2,FALSE)) | V84: =IF(B84="","",VLOOKUP(B84,MATERIAL!A$3:C$531,3,FALSE)) | AB84: =SUM(W84:AA84) -> 0
A85: 10 | C85: =IF(B85="","",VLOOKUP(B85,MATERIAL!A:C,2,FALSE)) | V85: =IF(B85="","",VLOOKUP(B85,MATERIAL!A$3:C$531,3,FALSE)) | AB85: =SUM(W85:AA85) -> 0
A86: 11 | C86: =IF(B86="","",VLOOKUP(B86,MATERIAL!A:C,2,FALSE)) | V86: =IF(B86="","",VLOOKUP(B86,MATERIAL!A$3:C$531,3,FALSE)) | AB86: =SUM(W86:AA86) -> 0
A87: 12 | C87: =IF(B87="","",VLOOKUP(B87,MATERIAL!A:C,2,FALSE)) | V87: =IF(B87="","",VLOOKUP(B87,MATERIAL!A$3:C$531,3,FALSE)) | AB87: =SUM(W87:AA87) -> 0
