Workbook

Sheet Preenchimentos Automatico
A1: EQUIPE | B1: CAPITALIZAÇÃO | C1: N° CONTRATO | D1: NATUREZA DO SERVIÇO | E1: CRS | F1: PRESTADORA
A2: DIN-LVCB01 | B2: EQUIPE PESADA FIXA LV | C2: 2019044301 | D2: LV | E2: ME | F2: DÍNAMO

Sheet Planilha1
A1: cod_grupo | B1: descricao | C1: cod_mobra | D1: descricao | E1: instalar | F1: retirar | G1: instalar_emergencial | H1: retirar_emergencial
A2: 150 | B2: MANUTENÇÃO | C2: 92525 | D2: SERV. EMERG. HORARIO COMERCIAL - ADICIONAL 12% | E2: 1 | F2: 0 | G2: 0 | H2: 0
A3: 500 | B3: SAP | C3: 6046 | D3: DESAT CHAVE FUSIVEL 3 OP < 34,5 KV | E3: 0 | F3: 38.28 | G3: 0 | H3: 0
A4: 500 | B4: SAP | C4: 6071 | D4: INST CHAVE FUSIVEL < 34,5 KV LM | E4: 95.72 | F4: 0 | G4: 0 | H4: 0
A5: 500 | B5: SAP | C5: 6073 | D5: INST CHAVE FUSIVEL 3 OP < 34,5 KV | E5: 124.44 | F5: 0 | G5: 0 | H5: 0
A6: 500 | B6: SAP | C6: 6074 | D6: INST CHAVE FUSIVEL 3 OP => 34,5 KV | E6: 124.44 | F6: 0 | G6: 0 | H6: 0
A7: 500 | B7: SAP | C7: 6083 | D7: INST PARA-RAIOS RD => 34,5 KV LM | E7: 95.72 | F7: 0 | G7: 0 | H7: 0
A8: 500 | B8: SAP | C8: 6137 | D8: LIMP FAIXA SERVIDAO MECANIZADA | E8: 2758.72 | F8: 0 | G8: 0 | H8: 0
A9: 500 | B9: SAP | C9: 6220 | D9: INST CAIXA MED CPREDE 1 MEDID ELETROM LM | E9: 143.58 | F9: 0 | G9: 0 | H9: 0
A10: 500 | B10: SAP | C10: 6227 | D10: DESAT CX MED CP-REDE P/ 3 OU 4 MEDID LM | E10: 0 | F10: 191.44 | G10: 0 | H10: 0
A11: 500 | B11: SAP | C11: 6235 | D11: INST CONEC RD SEC LM | E11: 9.58 | F11: 0 | G11: 0 | H11: 0
A12: 500 | B12: SAP | C12: 6252 | D12: SERV AB/FEC VAL ATER EM TERRA | E12: 17.23 | F12: 0 | G12: 0 | H12: 0
A13: 500 | B13: SAP | C13: 6281 | D13: DESAT ESTAI ANCORA CHUMBADO ROCHA LM | E13: 0 | F13: 95.72 | G13: 0 | H13: 0
... A192: 500 | B192: SAP | C192: 6586 | D192: INST ESTR PRIM DN4-SEM CHAVE LM | E192: 478.61 | F192: 0 | G192: 0 | H192: 0
A193: 500 | B193: SAP | C193: 6589 | D193: INST ESTR PRIM U3-2/U2-3 LM | E193: 191.44 | F193: 0
A194: 500 | B194: SAP | C194: 6595 | D194: INST SAPATA PANTANO COM TAMBOR | E194: 1435.83 | F194: 0
A195: 500 | B195: SAP | C195: 6603 | D195: NIVELAR COND AT P/FASE LM | E195: 255.58 | F195: 0
A196: 500 | B196: SAP | C196: 6611 | D196: REMAN TRANSF MON LM | E196: 670.06 | F196: 287.17
A197: 500 | B197: SAP | C197: 6653 | D197: EST ILUM SUBST LUMIN FECHADA LM | E197: 100.51 | F197: 43.08
A198: 500 | B198: SAP | C198: 6656 | D198: INST ESTRUT PRIM N23/M23/B23 LM | E198: 478.61 | F198: 0
A199: 500 | B199: SAP | C199: 6671 | D199: ABERTURA FAIXA VEGETACAO DENSA C/TRATOR | E199: 6317.67 | F199: 0
A200: 500 | B200: SAP | C200: 6679 | D200: REINST CRUZAM AER FLY TAP BT JUMP LV | E200: 43.94 | F200: 18.83
A201: 500 | B201: SAP | C201: 6683 | D201: INST CAPACITOR MT MONOPOLAR LV | E201: 150.67 | F201: 0
A202: 500 | B202: SAP | C202: 6688 | D202: SERV TEC INST COBERT REDE FASE LV | E202: 448.87 | F202: 0
A203: 500 | B203: SAP | C203: 6690 | D203: INST CONECTOR REDE PRIMARIA LV | E203: 125.55 | F203: 0
A204: 500 | B204: SAP | C204: 6693 | D204: INST ESPACADOR LOSANG 50/185MM² LV | E204: 109.87 | F204: 0
... A581: 150 | B581: MANUTENÇÃO | C581: 92324 | D581: HORA DO COLABORADOR EM DISPONIBILIDADE PARA OUTRA REGIONAL - LM_x000D_ | E581: 87.11 | F581: 0

Sheet MATERIAL
A1: COD SISUP | B1: Texto breve de material (REVISADA) | C1: Unidade de medida básica
A2: 623 | B2: CABO CU MOLE 120MM2 750V PVC PT | C2: M
A3: 3752 | B3: AFASTADOR ISOL PILAR AC1020 10X100X320MM | C3: PC
A4: 3752 | B4: AFASTADOR ISOL PILAR AC1020 10X100X320MM | C4: PC
A5: 113 | B5: ALCA PREF DIS CA/CAA 2/0AWG 10,4-11,69MM | C5: PC
A6: 2814 | B6: ALCA PREF DIS CA/CAA 6AWG 4,62-5,15MM | C6: PC
A7: 121 | B7: ALCA PREF ESTAI 6,4MM HS/SM | C7: PC
A8: 90308 | B8: ALCA PREFORM DISTRIB ACO 120MM2/4/0AWG(CA/CAA) 875,0MM | C8: UN
A9: 90309 | B9: ALCA PREFORM DISTRIB ACO 336,4MCM(CA) 978,0MM | C9: UN
A10: 90310 | B10: ALCA PREFORM DISTRIB ACO 336,4MCM(CAA) 1000,0MM | C10: UN
A11: 90315 | B11: ALCA PREFORM DISTRIB ACO ALUM 1/0AWG(CA/CAA) 660,0MM | C11: UN
A12: 90303 | B12: ALCA PREFORM SERVICO ACO 10,0MM2 292,0MM | C12: UN
A13: 90305 | B13: ALCA PREFORM SERVICO ACO 25,0MM2/4 AWG(CAA) 445,0MM | C13: UN
... A478: 90645 | B478: ELO FUSIVEL DISTRIBUICAO TIPO K 25A 500MM BRANCO | C478: UN
A479: 90345 | B479: CONECTOR CUNHA CB-EST ALUM 5,88-8,01MM 2AWG VM | C479: UN | D479: 10001448 | E479: 0.225 | F479: KG | G479: C
A480: 90645 | B480: ELO FUSIVEL DISTRIBUICAO TIPO K 25A 500MM BRANCO | D480: 10001484 | E480: 0.09 | F480: KG | G480: C
A481: 90379 | B481: PARAFUSO ROSC TOTAL ACO CARB M16 400MM
A482: 90648 | B482: AFASTADOR ISOLADOR PILAR ACO GALV 100X320MM 10MM 320DAN | C482: PC
A483: 90301 | B483: ALCA PREF CORD ACO-ZN 6,40MM 5X2.18MM 460MM AMR | C483: UN
A484: 90013 | B484: ALCA PREF CORD ACO-ZN 9,50MM 6X2.54MM 965MM LRJ | C484: UN
A485: 113 | B485: ALCA PREF DIS CA/CAA 2/0AWG 10,4-11,69MM | C485: PC
A486: 2814 | B486: ALCA PREF DIS CA/CAA 6AWG 4,62-5,15MM | C486: PC
A487: 90315 | B487: ALCA PREF DISTR ACO-ALUM 9,27-10,40MM 660MM AMR | C487: UN
A488: 90308 | B488: ALCA PREF DISTR ACO-ZINC 13,10-14,65MM 865MM VRM | C488: UN
A489: 90309 | B489: ALCA PREF DISTR ACO-ZINC 16,20-18,15MM 980MM VRD | C489: UN
A490: 90307 | B490: ALCA PREF DISTR ACO-ZINC 9,15-10,25MM 670MM AMR | C490: UN
A491: 121 | B491: ALCA PREF ESTAI 6,4MM HS/SM | C491: PC
A492: 90303 | B492: ALCA PREF SERV ACO-ZINC 3,90-4,30MM 345MM MRM | C492: UN
A493: 90305 | B493: ALCA PREF SERV ACO-ZINC 6,00-6,70MM 330MM LRJ | C493: UN
... A515: 90263 | B515: CABO ALUM NU CAA/ASCR 1F 1/0AWG RAVEN | C515: KG
A516: 90262 | B516: CABO ALUM NU CAA/ASCR 1F 2AWG SPARROW
A517: 90264 | B517: CABO ALUM NU CAA/ASCR 1F 4/0AWG PENGUIN | C517: KG
A518: 90267 | B518: CABO ALUM PROT SPL XLPE 1F 15,0KV 120MM2 BLOQ CNZ | C518: M
A519: 90266 | B519: CABO ALUM PROT SPL XLPE 1F 15,0KV 50MM2 BLOQ CNZ | C519: M
A520: 90292 | B520: CABO ALUM PROT SPL XLPE 1F 36,2KV 120MM2 BLOQ CNZ | C520: M
A521: 90291 | B521: CABO ALUM PROT SPL XLPE 1F 36,2KV 70MM2 BLOQ CNZ | C521: M
A522: 90294 | B522: CABO COBR PROT SPL XLPE 1F 15,0KV 16MM2 BLOQ CNZ | C522: M
A523: 91206 | B523: CABO ALUM PROT SPL XLPE 1F 15,0KV 150MM2 BLOQ CNZ | C523: M
A524: 91462 | B524: CABO COBRE ISOLAD 450/750V BWF/PVC 120MM2 CL2/4/5 PRT | C524: M
A525: 3098 | B525: CABO ISOL 750V COBRE PVC/BWF 10MM2 1F CL2 PT | C525: M
A526: 90887 | B526: CAPA PROT CONECTOR CUNHA 15KV 131X80MM SERIE VERM | C526: PC
A527: 90888 | B527: CAPA PROT CONECTOR CUNHA 15KV 166X100MM SERIE AZUL | C527: PC
A528: 90968 | B528: CAPA PROT PEAD TRANSF BT 1,2 KV 247X85X70MM 2X24MM | C528: UN
... A568: 90490 | B568: CONECTOR ATERR CUNHA COBRE CB/HST 16-25MM2 14,3MM | C568: UN
A569: 90796 | B569: CONECTOR AMPACT CN2
A570: 90796 | B570: CONECTOR CUNHA ALUM CN-02 15,24-17,37/11,68,17,37MM AZL | C570: UN
A571: 90799 | B571: CONECTOR CUNHA ALUM CN-03 15,24-17,37/8,23-15,24MM AZL | C571: UN
A572: 90793 | B572: CONECTOR CUNHA ALUM CN-04 15,24-17,37/6,55-14,27MM AZL | C572: UN
A573: 90790 | B573: CONECTOR CUNHA ALUM CN-06 9,25-14,53/6,55-14,53MM AZL | C573: UN
A574: 90791 | B574: CONECTOR CUNHA ALUM CN-10 8,23-14,53/4,11-11,79MM AZL | C574: UN
A575: 90787 | B575: CONECTOR CUNHA ALUM CN-12 5,18-8,38/4,11-6,55MM VRM | C575: UN
A576: 90797 | B576: CONECTOR CUNHA ALUM CN-13 6,55-10,11/5,18-8,38MM VRM | C576: UN
A577: 90798 | B577: CONECTOR CUNHA ALUM CN-15 10,40-14,53/10,40-14,53MM AZL | C577: UN
A578: 90795 | B578: CONECTOR CUNHA ALUM CN-16 16,90-18,30/11,80-14,31MM AZL | C578: UN
A579: 90800 | B579: CONECTOR CUNHA ALUM CN-17 16,90-18,30/7,42-11,35MM AZL | C579: UN
A580: 2914 | B580: CONECTOR CUNHA ALUMINIO 10,11MM/ 8,38MM VM | C580: PC
A581: 90347 | B581: CONECTOR CUNHA CB-EST ALUM 11,20-13,30MM 2AWG AZ | C581: UN
... A607: 192 | B607: EMENDA PREFORMADA CONDUTORA ACO CARB 4AWG 635MM | C607: PC
A608: 91707 | B608: EMENDA PRED CON MET CAA 2AWG 7,89-8,27MM
A609: 2928 | B609: EMENDA PREFORMADA TOTAL ACO CARB 1/0AWG 1475MM | C609: PC
A610: 90567 | B610: ESPACADOR LOSANGULAR PEAD 15KV 340X460MM TRAV CNZ/PRT | C610: PC
A611: 90399 | B611: ESTRIBO P/ BRACO TIPO L ACO GALV 140X70X50MM 400DAN | C611: UN
A612: 90391 | B612: FIO AMARRACAO ALUMINIO MOLE 1F 6AWG 4.11MM 80DAN | C612: KG
A613: 90392 | B613: FITA LISA P/ AMARRACAO CABO ALUM 1F 10,0X1,0MM | C613: KG
A614: 90515 | B614: FIXADOR PERFIL U ACO GALV 37X76X176MM 150DAN | C614: UN
A615: 90448 | B615: GANCHO OLHAL ACO GALV 130X88X13MM 50KN S/TRAVA | C615: UN
A616: 90450 | B616: GRAMPO ANCOR DIELETR SINGLE 15KV 18,8-21,3MM 120MM2 400DAN | C616: UN
A617: 90451 | B617: GRAMPO ANCOR DIELETR SINGLE 15KV 21,8-24,3MM 185MM2 400DAN | C617: UN
A618: 90455 | B618: GRAMPO ANCOR DIELETR SINGLE 36,2KV 25,3-28,6MM 70MM2 400DAN | C618: UN
A619: 90456 | B619: GRAMPO ANCOR DIELETR SINGLE 36,2KV 28,6-31,9MM 120MM2 400DAN | C619: UN
A620: 2941 | B620: HASTE ANCORA CERCA SAE1045 GALV 5100KGF 16,0MM 2,40M | C620: PC
... A711: 90413 | B711: SEPARADOR VERTICAL PEAD 36,2KV 950MM TRAV CNZ/PRT | C711: UN
A712: 90522 | B712: SUPORTE FORMATO L ENERGISA EPD-57035-053
A713: 3021 | B713: SUPORTE FORMATO L ENERGISA EPD-57035-053 | C713: PC
A714: 90656 | B714: SUPORTE HORIZONTAL 15 KV 300X200X300MM 200 DAN | C714: UN
A715: 4096 | B715: SUPORTE L ENERGISA DES EPD- 57035-054 | C715: PC
A716: 252 | B716: SUPORTE L ISOLADOR PILAR 265X107X5MM | C716: PC
A717: 90519 | B717: SUPORTE P/CHAVE FACA INCLINADO 45 15KV 220X169X220MM | C717: UN
A718: 90520 | B718: SUPORTE P/CHAVE FACA INCLINADO 45 25/35KV 320X245X320MM | C718: UN
A719: 3095 | B719: SUPORTE T ENERGISA DES EPD-57035-058 540MM | C719: PC
A720: 3096 | B720: SUPORTE T ENERGISA DES EPD-57035-058 800MM | C720: PC
A721: 90422 | B721: SUPORTE TRANSF ESP PST DT ACO GALV 230X150X10MM 3000DAN | C721: UN
A722: 90423 | B722: SUPORTE TRANSF ESP PST DT ACO GALV 360X76X10MM 3000DAN | C722: UN
A723: 90427 | B723: SUPORTE TRANSF PST CIRC ACO GALV 230MM 76X8MM 3000DAN | C723: UN
A724: 90530 | B724: SUPORTE TRANSF PST CIRC ACO GALV 250MM 76X8MM 3000DAN | C724: UN
... A747: 90083 | B747: TRANSF DISTR AER OMI 3F 34,5KV 220/127V 75KVA CL2 4TP | C747: UN

Sheet FECHAMENTO
A1: Serviços Emergenciais Linha Viva | N1: =SUM(N3:N4) -> 0 | O1: =SUM(O3:O4) -> 0 | P1: =SUM(P3:P4) -> 0
A2: LOTE ENVIADO | B2: DATA ENVIO LOTE | C2: Nº CONTRATO | D2: DATA EXECUÇÃO | E2: EQUIPE | F2: IDENTIFICAÇÃO EQUIPAMENTO | G2: CODIGO ACIONAMENTO | H2: INTERVENÇÃO ACIONAMENTO | I2: NOTA DO SGM | J2: APOIO A ENG LM | K2: CÓDIGO EXTERNO | L2: ENG LV | M2: OS SECUNDARIA | N2: VALOR | O2: VALOR FISCAL | P2: DIFERENÇA | Q2: Nº DA OBRA EMERGENCIAL | R2: OBSERVAÇÕES ENERGISA | S2: OBSERVAÇÕES DINAMO
A3: 44707 | B3: 44707 | C3: 2022000901 | D3: 44698 | E3: E-10 | F3: 41378876 | G3: Gustavo | H3: 8916858006 | J3: SIM | L3: ENG LV CBO1 | M3: EMT-RD-ME 6042/2022 | N3: ='ENG LVCBO1'!AK37 -> 0 | P3: =O3-N3 -> 0
P4: =O4-N4 -> 0

Sheet Mão de Obra
F1: 295.91765
A2: CÓDIGOS SIAGO | B2: CÓDIGOS SGM | C2: DESCRIÇÃO BÁSICA | D2: UNIDADE | E2: T/H | F2: R$
A3: 92525 | B3: I6770 | C3: SERV. EMERG. HORARIO COMERCIAL - ADICIONAL 12% | E3: 0.02 | F3: 1
A4: 6046 | C4: DESAT CHAVE FUSIVEL 3 OP < 34,5 KV | E4: 6 | F4: 38.28
A5: 6071 | C5: INST CHAVE FUSIVEL < 34,5 KV LM | E5: 0.06 | F5: 95.72
A6: 6073 | C6: INST CHAVE FUSIVEL 3 OP < 34,5 KV | E6: 0.01 | F6: 124.44
A7: 6074 | C7: INST CHAVE FUSIVEL 3 OP => 34,5 KV | E7: 0.02 | F7: 124.44
A8: 6083 | C8: INST PARA-RAIOS RD => 34,5 KV LM | E8: 0.01 | F8: 95.72
A9: 6137 | C9: LIMP FAIXA SERVIDAO MECANIZADA | E9: 0.37 | F9: 2758.72
A10: 6220 | C10: INST CAIXA MED CPREDE 1 MEDID ELETROM LM | E10: 0.42 | F10: 143.58
A11: 6227 | C11: DESAT CX MED CP-REDE P/ 3 OU 4 MEDID LM | E11: 0.42 | F11: 191.44
A12: 6235 | C12: INST CONEC RD SEC LM | E12: 1.19 | F12: 9.58
A13: 6252 | C13: SERV AB/FEC VAL ATER EM TERRA | E13: 0.36 | F13: 17.23
A14: 6281 | C14: DESAT ESTAI ANCORA CHUMBADO ROCHA LM | E14: 0.43 | F14: 95.72
A15: 6298 | C15: DESAT RAMAL SERVICO TRIFASICO LM | E15: 1 | F15: 19.14
... A195: 6595 | C195: INST SAPATA PANTANO COM TAMBOR | E195: 1 | F195: 1435.83
A196: 6603 | C196: NIVELAR COND AT P/FASE LM | F196: 255.58
A197: 6611 | C197: REMAN TRANSF MON LM | F197: 957.23
A198: 6653 | C198: EST ILUM SUBST LUMIN FECHADA LM | F198: 143.59
A199: 6656 | C199: INST ESTRUT PRIM N23/M23/B23 LM | F199: 478.61
A200: 6671 | C200: ABERTURA FAIXA VEGETACAO DENSA C/TRATOR | F200: 6317.67
A201: 6679 | C201: REINST CRUZAM AER FLY TAP BT JUMP LV | F201: 62.77
A202: 6683 | C202: INST CAPACITOR MT MONOPOLAR LV | F202: 150.67
A203: 6688 | C203: SERV TEC INST COBERT REDE FASE LV | F203: 448.87
A204: 6690 | C204: INST CONECTOR REDE PRIMARIA LV | F204: 125.55
A205: 6693 | C205: INST ESPACADOR LOSANG 50/185MM² LV | F205: 109.87
A206: 6695 | C206: INST ESTAI CRUZETA A CRUZETA LV | F206: 784.74
A207: 6696 | C207: INSTALACAO ESTRIBO EM REDE EXIST AT LV | F207: 62.78
... A582: 92324 | C582: HORA DO COLABORADOR EM DISPONIBILIDADE PARA OUTRA REGIONAL - LM_x000D_ | F582: 87.11

Sheet ENG LVCBO1
J2: Medição do Serviço Executado pela Equipe de Linha Viva - Construção | AE2: ENG-LV Nº
B5: EQUIPE : | G5: KM INICIAL : | M5: KM FINAL: | P5: KM RODADO: | Q5: =N5-K5 -> 0 | T5: DATA: | W5: =U5 -> 0 | AE5: OBRA: OS:
B8: ENDEREÇO: | X8: OS TABLET/EXTERNA:
B11: RESPONSAVEIS PELO SERVIÇO: | M11: OPERADOR: | R11: TIPO DE SERVIÇO: | T11: EMERGENCIAL | X11: ID: | AE11: Cód. Acionamento:
AE12: Intervenção:
B13: ALIMENTADOR: | G13: S/E: | M13: CHAVE: | P13: PT: | AE13: Nota SGM:
B15: OBSERVAÇÕES:
B20: CÓDIGO | C20: DESCRIÇÃO MÃO DE OBRA | S20: UN | T20: VALOR UNITARIO (R$) | AJ20: Qtotal | AK20: R$
C21: =IF(B21="","",VLOOKUP(B21,'Mão de Obra'!A:F,3,FALSE)) | S21: =IF(B21="","",VLOOKUP(B21,'Mão de Obra'!A:F,4,FALSE)) | T21: =IF(B21="","",VLOOKUP(B21,'Mão de Obra'!A:F,6,FALSE)) | AJ21: =U21 -> 0 | AK21: =IF(U21="","",(AJ21*T21))
C22: =IF(B22="","",VLOOKUP(B22,'Mão de Obra'!A:F,3,FALSE)) | S22: =IF(B22="","",VLOOKUP(B22,'Mão de Obra'!A:F,4,FALSE)) | T22: =IF(B22="","",VLOOKUP(B22,'Mão de Obra'!A:F,6,FALSE)) | AJ22: =U22 -> 0 | AK22: =IF(U22="","",(AJ22*T22))
C23: =IF(B23="","",VLOOKUP(B23,'Mão de Obra'!A:F,3,FALSE)) | S23: =IF(B23="","",VLOOKUP(B23,'Mão de Obra'!A:F,4,FALSE)) | T23: =IF(B23="","",VLOOKUP(B23,'Mão de Obra'!A:F,6,FALSE)) | AJ23: =U23 -> 0 | AK23: =IF(U23="","",(AJ23*T23))
C24: =IF(B24="","",VLOOKUP(B24,'Mão de Obra'!A:F,3,FALSE)) | S24: =IF(B24="","",VLOOKUP(B24,'Mão de Obra'!A:F,4,FALSE)) | T24: =IF(B24="","",VLOOKUP(B24,'Mão de Obra'!A:F,6,FALSE)) | AJ24: =U24 -> 0 | AK24: =IF(U24="","",(AJ24*T24))
C25: =IF(B25="","",VLOOKUP(B25,'Mão de Obra'!A:F,3,FALSE)) | S25: =IF(B25="","",VLOOKUP(B25,'Mão de Obra'!A:F,4,FALSE)) | T25: =IF(B25="","",VLOOKUP(B25,'Mão de Obra'!A:F,6,FALSE)) | AJ25: =U25 -> 0 | AK25: =IF(U25="","",(AJ25*T25))
C26: =IF(B26="","",VLOOKUP(B26,'Mão de Obra'!A:F,3,FALSE)) | S26: =IF(B26="","",VLOOKUP(B26,'Mão de Obra'!A:F,4,FALSE)) | T26: =IF(B26="","",VLOOKUP(B26,'Mão de Obra'!A:F,6,FALSE)) | AJ26: =U26 -> 0 | AK26: =IF(U26="","",(AJ26*T26))
C27: =IF(B27="","",VLOOKUP(B27,'Mão de Obra'!A:F,3,FALSE)) | S27: =IF(B27="","",VLOOKUP(B27,'Mão de Obra'!A:F,4,FALSE)) | T27: =IF(B27="","",VLOOKUP(B27,'Mão de Obra'!A:F,6,FALSE)) | AJ27: =U27 -> 0 | AK27: =IF(U27="","",(AJ27*T27))
C28: =IF(B28="","",VLOOKUP(B28,'Mão de Obra'!A:F,3,FALSE)) | S28: =IF(B28="","",VLOOKUP(B28,'Mão de Obra'!A:F,4,FALSE)) | T28: =IF(B28="","",VLOOKUP(B28,'Mão de Obra'!A:F,6,FALSE)) | AJ28: =U28 -> 0 | AK28: =IF(U28="","",(AJ28*T28))
C29: =IF(B29="","",VLOOKUP(B29,'Mão de Obra'!A:F,3,FALSE)) | S29: =IF(B29="","",VLOOKUP(B29,'Mão de Obra'!A:F,4,FALSE)) | T29: =IF(B29="","",VLOOKUP(B29,'Mão de Obra'!A:F,6,FALSE)) | AJ29: =U29 -> 0 | AK29: =IF(U29="","",(AJ29*T29))
C30: =IF(B30="","",VLOOKUP(B30,'Mão de Obra'!A:F,3,FALSE)) | S30: =IF(B30="","",VLOOKUP(B30,'Mão de Obra'!A:F,4,FALSE)) | T30: =IF(B30="","",VLOOKUP(B30,'Mão de Obra'!A:F,6,FALSE)) | AJ30: =U30 -> 0 | AK30: =IF(U30="","",(AJ30*T30))
C31: =IF(B31="","",VLOOKUP(B31,'Mão de Obra'!A:F,3,FALSE)) | S31: =IF(B31="","",VLOOKUP(B31,'Mão de Obra'!A:F,4,FALSE)) | T31: =IF(B31="","",VLOOKUP(B31,'Mão de Obra'!A:F,6,FALSE)) | AJ31: =U31 -> 0 | AK31: =IF(U31="","",(AJ31*T31))
C32: =IF(B32="","",VLOOKUP(B32,'Mão de Obra'!A:F,3,FALSE)) | S32: =IF(B32="","",VLOOKUP(B32,'Mão de Obra'!A:F,4,FALSE)) | T32: =IF(B32="","",VLOOKUP(B32,'Mão de Obra'!A:F,6,FALSE)) | AJ32: =U32 -> 0 | AK32: =IF(U32="","",(AJ32*T32))
... C36: =IF(B36="","",VLOOKUP(B36,'Mão de Obra'!A:F,3,FALSE)) | S36: =IF(B36="","",VLOOKUP(B36,'Mão de Obra'!A:F,4,FALSE)) | T36: =IF(B36="","",VLOOKUP(B36,'Mão de Obra'!A:F,6,FALSE)) | AJ36: =U36 -> 0 | AK36: =IF(U36="","",(AJ36*T36))
B37: SUB-TOTAL: | AK37: =SUM(AK21:AK36) -> 0
B39: 26376 | D39: SERV. EMERG. FORA DO HORARIO COMERCIAL-ADICIONAL 30% | AB39: ADICIONAL | AE39: =IF(AG39>0,($AK$37*0.3),"0") -> 0 | AK39: =AE39 -> 0
B40: 92525 | D40: SERV. EMERG. HORARIO COMERCIAL - ADICIONAL 12% | AB40: ADICIONAL | AE40: =IF(AG40>0,($AK$37*0.12),"0") -> 0 | AK40: =AE40 -> 0
B41: TOTAL | AK41: =SUM(AK40+AK39+AK37) -> 0
B43: CÓDIGO | C43: DESCRIÇÃO DO MATERIAL APLICADO | T43: UN | U43: =U20 -> 0 | AK43: QTDE
C44: =IF(B44="","",VLOOKUP(B44,MATERIAL!A:C,2,FALSE)) | T44: =IF(B44="","",VLOOKUP(B44,MATERIAL!A:C,3,FALSE)) | AK44: =U44 -> 0
C45: =IF(B45="","",VLOOKUP(B45,MATERIAL!A:C,2,FALSE)) | T45: =IF(B45="","",VLOOKUP(B45,MATERIAL!A:C,3,FALSE)) | AK45: =U45 -> 0
C46: =IF(B46="","",VLOOKUP(B46,MATERIAL!A:C,2,FALSE)) | T46: =IF(B46="","",VLOOKUP(B46,MATERIAL!A:C,3,FALSE)) | AK46: =U46 -> 0
C47: =IF(B47="","",VLOOKUP(B47,MATERIAL!A:C,2,FALSE)) | T47: =IF(B47="","",VLOOKUP(B47,MATERIAL!A:C,3,FALSE)) | AK47: =U47 -> 0
C48: =IF(B48="","",VLOOKUP(B48,MATERIAL!A:C,2,FALSE)) | T48: =IF(B48="","",VLOOKUP(B48,MATERIAL!A:C,3,FALSE)) | AK48: =U48 -> 0
C49: =IF(B49="","",VLOOKUP(B49,MATERIAL!A:C,2,FALSE)) | T49: =IF(B49="","",VLOOKUP(B49,MATERIAL!A:C,3,FALSE)) | AK49: =U49 -> 0
C50: =IF(B50="","",VLOOKUP(B50,MATERIAL!A:C,2,FALSE)) | T50: =IF(B50="","",VLOOKUP(B50,MATERIAL!A:C,3,FALSE)) | AK50: =U50 -> 0
C51: =IF(B51="","",VLOOKUP(B51,MATERIAL!A:C,2,FALSE)) | T51: =IF(B51="","",VLOOKUP(B51,MATERIAL!A:C,3,FALSE)) | AK51: =U51 -> 0
C52: =IF(B52="","",VLOOKUP(B52,MATERIAL!A:C,2,FALSE)) | T52: =IF(B52="","",VLOOKUP(B52,MATERIAL!A:C,3,FALSE)) | AK52: =U52 -> 0
C53: =IF(B53="","",VLOOKUP(B53,MATERIAL!A:C,2,FALSE)) | T53: =IF(B53="","",VLOOKUP(B53,MATERIAL!A:C,3,FALSE)) | AK53: =U53 -> 0
C54: =IF(B54="","",VLOOKUP(B54,MATERIAL!A:C,2,FALSE)) | T54: =IF(B54="","",VLOOKUP(B54,MATERIAL!A:C,3,FALSE)) | AK54: =U54 -> 0
C55: =IF(B55="","",VLOOKUP(B55,MATERIAL!A:C,2,FALSE)) | T55: =IF(B55="","",VLOOKUP(B55,MATERIAL!A:C,3,FALSE)) | AK55: =U55 -> 0
... C58: =IF(B58="","",VLOOKUP(B58,MATERIAL!A:C,2,FALSE)) | T58: =IF(B58="","",VLOOKUP(B58,MATERIAL!A:C,3,FALSE)) | AK58: =U58 -> 0
B60: CÓDIGO | C60: DESCRIÇÃO DO MATERIAL RETIRADO | T60: UN | U60: REUTILIZADO NO SERVIÇO | Y60: BOM | AB60: SUCATA | AE60: DESCARTE | AH60: REFORMA | AK60: QTDE
C61: =IF(B61="","",VLOOKUP(B61,MATERIAL!A:C,2,FALSE)) | T61: =IF(B61="","",VLOOKUP(B61,MATERIAL!A:C,3,FALSE)) | AK61: =IF(T61="","",(SUM(U61:AJ61)))
C62: =IF(B62="","",VLOOKUP(B62,MATERIAL!A:C,2,FALSE)) | T62: =IF(B62="","",VLOOKUP(B62,MATERIAL!A:C,3,FALSE)) | AK62: =IF(T62="","",(SUM(U62:AJ62)))
C63: =IF(B63="","",VLOOKUP(B63,MATERIAL!A:C,2,FALSE)) | T63: =IF(B63="","",VLOOKUP(B63,MATERIAL!A:C,3,FALSE)) | AK63: =IF(T63="","",(SUM(U63:AJ63)))
C64: =IF(B64="","",VLOOKUP(B64,MATERIAL!A:C,2,FALSE)) | T64: =IF(B64="","",VLOOKUP(B64,MATERIAL!A:C,3,FALSE)) | AK64: =IF(T64="","",(SUM(U64:AJ64)))
C65: =IF(B65="","",VLOOKUP(B65,MATERIAL!A:C,2,FALSE)) | T65: =IF(B65="","",VLOOKUP(B65,MATERIAL!A:C,3,FALSE)) | AK65: =IF(T65="","",(SUM(U65:AJ65)))
C66: =IF(B66="","",VLOOKUP(B66,MATERIAL!A:C,2,FALSE)) | T66: =IF(B66="","",VLOOKUP(B66,MATERIAL!A:C,3,FALSE)) | AK66: =IF(T66="","",(SUM(U66:AJ66)))
C67: =IF(B67="","",VLOOKUP(B67,MATERIAL!A:C,2,FALSE)) | T67: =IF(B67="","",VLOOKUP(B67,MATERIAL!A:C,3,FALSE)) | AK67: =IF(T67="","",(SUM(U67:AJ67)))
C68: =IF(B68="","",VLOOKUP(B68,MATERIAL!A:C,2,FALSE)) | T68: =IF(B68="","",VLOOKUP(B68,MATERIAL!A:C,3,FALSE)) | AK68: =IF(T68="","",(SUM(U68:AJ68)))
C69: =IF(B69="","",VLOOKUP(B69,MATERIAL!A:C,2,FALSE)) | T69: =IF(B69="","",VLOOKUP(B69,MATERIAL!A:C,3,FALSE)) | AK69: =IF(T69="","",(SUM(U69:AJ69)))
C70: =IF(B70="","",VLOOKUP(B70,MATERIAL!A:C,2,FALSE)) | T70: =IF(B70="","",VLOOKUP(B70,MATERIAL!A:C,3,FALSE)) | AK70: =IF(T70="","",(SUM(U70:AJ70)))
C71: =IF(B71="","",VLOOKUP(B71,MATERIAL!A:C,2,FALSE)) | T71: =IF(B71="","",VLOOKUP(B71,MATERIAL!A:C,3,FALSE)) | AK71: =IF(T71="","",(SUM(U71:AJ71)))
C72: =IF(B72="","",VLOOKUP(B72,MATERIAL!A:C,2,FALSE)) | T72: =IF(B72="","",VLOOKUP(B72,MATERIAL!A:C,3,FALSE)) | AK72: =IF(T72="","",(SUM(U72:AJ72)))
... C75: =IF(B75="","",VLOOKUP(B75,MATERIAL!A:C,2,FALSE)) | T75: =IF(B75="","",VLOOKUP(B75,MATERIAL!A:C,3,FALSE)) | AK75: =IF(T75="","",(SUM(U75:AJ75)))
